{
  "ok": true,
  "stale": false,
  "updated_at": "2026-06-30T13:01:14+08:00",
  "generated_at": "2026-06-30T13:01:14+08:00",
  "source": "tencent",
  "total_count": 5185,
  "message": "success",
  "thresholds": [
    10.0,
    5.0,
    2.0
  ],
  "limit": 120,
  "chip_threshold": null,
  "require_chip": false,
  "require_holder_decline": true,
  "holder_stats": {
    "scanned": 164,
    "ok": 162,
    "declined": 108,
    "failed": 2
  },
  "min_volume_ratio": 1.5,
  "chip_stats": {
    "scanned": 0,
    "ok": 0,
    "failed": 0
  },
  "buckets": {
    "10": [
      {
        "code": "603956",
        "name": "威派格",
        "price": 6.34,
        "pct": -1.09,
        "amount": 454600000.0,
        "turnover": 12.25,
        "vol_ratio": 4.77,
        "pe": -15.56,
        "pe_ttm": -24.94,
        "pb": 1.96,
        "total_cap": 3613000000.0000005,
        "float_cap": 3613000000.0000005,
        "main_net": null,
        "concepts": [
          "机械设备",
          "专用设备",
          "其他专用设备",
          "上海板块",
          "题材股",
          "破增发价股"
        ],
        "score": 116.84,
        "holder_num": 35459.0,
        "holder_change_ratio": -12.924217867492,
        "holder_avg_shares": 16072.2605262416,
        "holder_date": "2026-03-31"
      },
      {
        "code": "002038",
        "name": "双鹭药业",
        "price": 5.69,
        "pct": 1.97,
        "amount": 322940000.0,
        "turnover": 6.56,
        "vol_ratio": 2.17,
        "pe": -16.97,
        "pe_ttm": -12.2,
        "pb": 1.15,
        "total_cap": 4847000000.0,
        "float_cap": 5846000000.0,
        "main_net": null,
        "concepts": [
          "医药生物",
          "化学制药",
          "化学制剂",
          "北京板块",
          "最近多板",
          "东方财富热股"
        ],
        "score": 112.33,
        "holder_num": 62934.0,
        "holder_change_ratio": -8.484927801771,
        "holder_avg_shares": 16324.2444465631,
        "holder_date": "2026-06-18"
      },
      {
        "code": "002728",
        "name": "特一药业",
        "price": 9.0,
        "pct": 2.27,
        "amount": 318620000.0,
        "turnover": 7.04,
        "vol_ratio": 2.72,
        "pe": 44.83,
        "pe_ttm": 60.89,
        "pb": 2.61,
        "total_cap": 4512000000.0,
        "float_cap": 4620000000.0,
        "main_net": null,
        "concepts": [
          "医药生物",
          "中药Ⅱ",
          "中药Ⅲ",
          "广东板块",
          "2025年报预增",
          "破增发价股"
        ],
        "score": 108.84,
        "holder_num": 74487.0,
        "holder_change_ratio": -8.621726062688,
        "holder_avg_shares": 6891.2670935868,
        "holder_date": "2026-03-31"
      },
      {
        "code": "002628",
        "name": "成都路桥",
        "price": 5.35,
        "pct": 10.08,
        "amount": 309340000.0,
        "turnover": 7.88,
        "vol_ratio": 4.96,
        "pe": 75.16,
        "pe_ttm": -58.48,
        "pb": 1.44,
        "total_cap": 4033000000.0,
        "float_cap": 4050000000.0,
        "main_net": null,
        "concepts": [
          "建筑装饰",
          "基础建设",
          "基建市政工程",
          "四川板块",
          "破发股",
          "最近多板"
        ],
        "score": 107.8,
        "holder_num": 46733.0,
        "holder_change_ratio": -21.666471110813,
        "holder_avg_shares": 16200.5523933837,
        "holder_date": "2026-03-31"
      },
      {
        "code": "002255",
        "name": "海陆重工",
        "price": 9.82,
        "pct": 1.24,
        "amount": 330500000.0,
        "turnover": 5.33,
        "vol_ratio": 2.62,
        "pe": 19.71,
        "pe_ttm": 18.27,
        "pb": 1.78,
        "total_cap": 6265000000.0,
        "float_cap": 8159000000.0,
        "main_net": null,
        "concepts": [
          "电力设备",
          "其他电源设备Ⅱ",
          "火电设备",
          "江苏板块",
          "最近多板",
          "昨日高振幅"
        ],
        "score": 107.69,
        "holder_num": 100492.0,
        "holder_change_ratio": -5.764307617288,
        "holder_avg_shares": 8268.13134378856,
        "holder_date": "2026-03-31"
      },
      {
        "code": "600299",
        "name": "安迪苏",
        "price": 7.89,
        "pct": -0.75,
        "amount": 343050000.0,
        "turnover": 1.4,
        "vol_ratio": 3.97,
        "pe": 19.88,
        "pe_ttm": 24.42,
        "pb": 1.24,
        "total_cap": 24299000000.0,
        "float_cap": 24299000000.0,
        "main_net": null,
        "concepts": [
          "基础化工",
          "化学制品",
          "食品及饲料添加剂",
          "北京板块",
          "中盘股",
          "昨日高振幅"
        ],
        "score": 105.54,
        "holder_num": 27474.0,
        "holder_change_ratio": -16.035573484918,
        "holder_avg_shares": 112097.956504331,
        "holder_date": "2026-03-31"
      },
      {
        "code": "002437",
        "name": "誉衡药业",
        "price": 2.66,
        "pct": -0.37,
        "amount": 305980000.0,
        "turnover": 5.33,
        "vol_ratio": 2.47,
        "pe": 15.62,
        "pe_ttm": 14.41,
        "pb": 2.48,
        "total_cap": 5586000000.0,
        "float_cap": 5931000000.0,
        "main_net": null,
        "concepts": [
          "医药生物",
          "化学制药",
          "化学制剂",
          "黑龙江",
          "2025年报预增",
          "2026一季报预增"
        ],
        "score": 99.76,
        "holder_num": 91300.0,
        "holder_change_ratio": -2.038626609442,
        "holder_avg_shares": 24423.5282146769,
        "holder_date": "2026-06-20"
      },
      {
        "code": "600228",
        "name": "返利科技",
        "price": 9.3,
        "pct": -8.73,
        "amount": 538630000.0,
        "turnover": 12.97,
        "vol_ratio": 2.6,
        "pe": -69.09,
        "pe_ttm": -61.15,
        "pb": 10.15,
        "total_cap": 3869000000.0,
        "float_cap": 3875000000.0,
        "main_net": null,
        "concepts": [
          "传媒",
          "数字媒体",
          "门户网站",
          "江西板块",
          "趋势股",
          "最近多板"
        ],
        "score": 98.44,
        "holder_num": 15500.0,
        "holder_change_ratio": -16.890080428954,
        "holder_avg_shares": 26882.0920645161,
        "holder_date": "2026-03-31"
      },
      {
        "code": "000566",
        "name": "海南海药",
        "price": 4.6,
        "pct": 1.32,
        "amount": 610150000.0,
        "turnover": 9.98,
        "vol_ratio": 2.89,
        "pe": -19.52,
        "pe_ttm": -13.62,
        "pb": 1341.87,
        "total_cap": 5965000000.0,
        "float_cap": 5968000000.0,
        "main_net": null,
        "concepts": [
          "医药生物",
          "化学制药",
          "化学制剂",
          "海南板块",
          "破增发价股",
          "最近多板"
        ],
        "score": 95.34,
        "holder_num": 112860.0,
        "holder_change_ratio": -3.914590747331,
        "holder_avg_shares": 11495.3493354599,
        "holder_date": "2026-03-31"
      },
      {
        "code": "002354",
        "name": "天娱数科",
        "price": 9.23,
        "pct": 1.32,
        "amount": 3367800000.0,
        "turnover": 22.33,
        "vol_ratio": 1.63,
        "pe": 126.25,
        "pe_ttm": -640.28,
        "pb": 11.11,
        "total_cap": 15005000000.000002,
        "float_cap": 15272000000.0,
        "main_net": null,
        "concepts": [
          "传媒",
          "广告营销",
          "营销代理",
          "辽宁板块",
          "题材股",
          "百日新高 "
        ],
        "score": 95.2,
        "holder_num": 186575.0,
        "holder_change_ratio": -1.342054750334,
        "holder_avg_shares": 8868.20753048372,
        "holder_date": "2026-03-31"
      },
      {
        "code": "002413",
        "name": "雷科防务",
        "price": 9.78,
        "pct": 5.84,
        "amount": 650140000.0,
        "turnover": 5.15,
        "vol_ratio": 2.46,
        "pe": -202.36,
        "pe_ttm": -195.81,
        "pb": 3.92,
        "total_cap": 12669000000.0,
        "float_cap": 12903000000.0,
        "main_net": null,
        "concepts": [
          "国防军工",
          "军工电子Ⅱ",
          "军工电子Ⅲ",
          "北京板块",
          "小盘成长",
          "小盘股"
        ],
        "score": 90.63,
        "holder_num": 333603.0,
        "holder_change_ratio": -5.08863719775,
        "holder_avg_shares": 3954.82272341676,
        "holder_date": "2026-06-18"
      },
      {
        "code": "600623",
        "name": "华谊集团",
        "price": 8.21,
        "pct": 5.53,
        "amount": 223640000.0,
        "turnover": 1.5,
        "vol_ratio": 2.48,
        "pe": 25.91,
        "pe_ttm": 30.79,
        "pb": 0.77,
        "total_cap": 15402000000.000002,
        "float_cap": 17401000000.0,
        "main_net": null,
        "concepts": [
          "基础化工",
          "化学原料",
          "煤化工",
          "上海板块",
          "破增发价股",
          "小盘价值"
        ],
        "score": 90.13,
        "holder_num": 18924.0,
        "holder_change_ratio": -10.189359783589,
        "holder_avg_shares": 34155.9777002748,
        "holder_date": "2014-09-30"
      },
      {
        "code": "002687",
        "name": "乔治白",
        "price": 5.05,
        "pct": 1.61,
        "amount": 182320000.0,
        "turnover": 8.75,
        "vol_ratio": 1.54,
        "pe": 57.52,
        "pe_ttm": 31.47,
        "pb": 1.67,
        "total_cap": 2088000000.0,
        "float_cap": 2549000000.0,
        "main_net": null,
        "concepts": [
          "纺织服饰",
          "服装家纺",
          "非运动服装",
          "浙江板块",
          "最近多板",
          "昨日高振幅"
        ],
        "score": 88.95,
        "holder_num": 14511.0,
        "holder_change_ratio": -4.614474462631,
        "holder_avg_shares": 34785.9893184481,
        "holder_date": "2026-06-18"
      },
      {
        "code": "600839",
        "name": "四川长虹",
        "price": 6.9,
        "pct": 4.39,
        "amount": 744490000.0,
        "turnover": 2.33,
        "vol_ratio": 2.62,
        "pe": 80.86,
        "pe_ttm": 42.93,
        "pb": 2.07,
        "total_cap": 31843000000.0,
        "float_cap": 31852000000.0,
        "main_net": null,
        "concepts": [
          "家用电器",
          "黑色家电",
          "彩电",
          "四川板块",
          "消费风格",
          "中盘股"
        ],
        "score": 88.23,
        "holder_num": 629922.0,
        "holder_change_ratio": -7.214863957202,
        "holder_avg_shares": 7328.27909169707,
        "holder_date": "2026-03-31"
      },
      {
        "code": "002212",
        "name": "天融信",
        "price": 5.99,
        "pct": 7.35,
        "amount": 487130000.0,
        "turnover": 6.86,
        "vol_ratio": 6.5,
        "pe": -17.53,
        "pe_ttm": 168.74,
        "pb": 0.74,
        "total_cap": 6989000000.0,
        "float_cap": 7065000000.000001,
        "main_net": null,
        "concepts": [
          "计算机",
          "软件开发",
          "横向通用软件",
          "广东板块",
          "破增发价股",
          "破净股"
        ],
        "score": 87.18,
        "holder_num": 111205.0,
        "holder_change_ratio": -4.0426266287,
        "holder_avg_shares": 10606.122737287,
        "holder_date": "2026-03-31"
      },
      {
        "code": "002587",
        "name": "奥拓电子",
        "price": 7.81,
        "pct": 10.0,
        "amount": 448130000.0,
        "turnover": 11.0,
        "vol_ratio": 1.99,
        "pe": 83.99,
        "pe_ttm": 408.02,
        "pb": 3.88,
        "total_cap": 4160000000.0,
        "float_cap": 5112000000.0,
        "main_net": null,
        "concepts": [
          "电子",
          "光学光电子",
          "LED",
          "广东板块",
          "2025年报扭亏",
          "昨日高振幅"
        ],
        "score": 87.15,
        "holder_num": 41799.0,
        "holder_change_ratio": -2.738737900223,
        "holder_avg_shares": 15587.5536735329,
        "holder_date": "2026-03-31"
      },
      {
        "code": "300708",
        "name": "聚灿光电",
        "price": 8.55,
        "pct": 7.01,
        "amount": 318030000.0,
        "turnover": 5.3,
        "vol_ratio": 2.37,
        "pe": 67.82,
        "pe_ttm": 46.36,
        "pb": 2.8,
        "total_cap": 6071000000.0,
        "float_cap": 8028000000.0,
        "main_net": null,
        "concepts": [
          "电子",
          "光学光电子",
          "LED",
          "江苏板块",
          "创业板综",
          "深股通"
        ],
        "score": 86.92,
        "holder_num": 72200.0,
        "holder_change_ratio": -3.217158176944,
        "holder_avg_shares": 13004.3648753463,
        "holder_date": "2026-06-10"
      },
      {
        "code": "600468",
        "name": "百利电气",
        "price": 6.08,
        "pct": 4.11,
        "amount": 387000000.0,
        "turnover": 5.98,
        "vol_ratio": 7.85,
        "pe": 64.76,
        "pe_ttm": 80.05,
        "pb": 3.24,
        "total_cap": 6613000000.0,
        "float_cap": 6613000000.0,
        "main_net": null,
        "concepts": [
          "电力设备",
          "电网设备",
          "配电设备",
          "天津板块",
          "2025年报扭亏",
          "破增发价股"
        ],
        "score": 86.24,
        "holder_num": 89993.0,
        "holder_change_ratio": -0.780586763101,
        "holder_avg_shares": 12086.888102408,
        "holder_date": "2026-03-31"
      },
      {
        "code": "002607",
        "name": "中公教育",
        "price": 1.77,
        "pct": -2.21,
        "amount": 477610000.0,
        "turnover": 4.68,
        "vol_ratio": 3.06,
        "pe": 57.67,
        "pe_ttm": 194.16,
        "pb": 13.57,
        "total_cap": 9812000000.0,
        "float_cap": 10916000000.0,
        "main_net": null,
        "concepts": [
          "社会服务",
          "教育",
          "培训教育",
          "安徽板块",
          "2025年报预减",
          "破发股"
        ],
        "score": 85.28,
        "holder_num": 256307.0,
        "holder_change_ratio": -5.161753442094,
        "holder_avg_shares": 24062.5476050205,
        "holder_date": "2026-03-31"
      },
      {
        "code": "000727",
        "name": "冠捷科技",
        "price": 2.7,
        "pct": 6.72,
        "amount": 557070000.0,
        "turnover": 4.62,
        "vol_ratio": 2.28,
        "pe": -10.81,
        "pe_ttm": -13.63,
        "pb": 6.78,
        "total_cap": 12230000000.0,
        "float_cap": 12230000000.0,
        "main_net": null,
        "concepts": [
          "电子",
          "光学光电子",
          "面板",
          "江苏板块",
          "小盘股",
          "低价股"
        ],
        "score": 84.11,
        "holder_num": 134000.0,
        "holder_change_ratio": -6.293706293706,
        "holder_avg_shares": 33802.7386567164,
        "holder_date": "2026-06-18"
      },
      {
        "code": "002930",
        "name": "宏川智慧",
        "price": 9.1,
        "pct": -4.01,
        "amount": 193450000.0,
        "turnover": 4.88,
        "vol_ratio": 2.06,
        "pe": 56.59,
        "pe_ttm": -9.63,
        "pb": 2.13,
        "total_cap": 3943000000.0,
        "float_cap": 4163000000.0000005,
        "main_net": null,
        "concepts": [
          "交通运输",
          "物流",
          "仓储物流",
          "广东板块",
          "最近多板",
          "昨日高振幅"
        ],
        "score": 82.46,
        "holder_num": 14451.0,
        "holder_change_ratio": -9.221684779195,
        "holder_avg_shares": 31658.0170230434,
        "holder_date": "2026-03-31"
      },
      {
        "code": "600222",
        "name": "太龙药业",
        "price": 7.12,
        "pct": -1.79,
        "amount": 229220000.0,
        "turnover": 5.42,
        "vol_ratio": 3.83,
        "pe": 392.71,
        "pe_ttm": 66.91,
        "pb": 2.54,
        "total_cap": 4086000000.0,
        "float_cap": 4086000000.0,
        "main_net": null,
        "concepts": [
          "医药生物",
          "中药Ⅱ",
          "中药Ⅲ",
          "河南板块",
          "最近多板",
          "昨日高振幅"
        ],
        "score": 81.74,
        "holder_num": 38752.0,
        "holder_change_ratio": -11.519053816471,
        "holder_avg_shares": 14809.2042475227,
        "holder_date": "2026-03-31"
      },
      {
        "code": "600576",
        "name": "祥源文旅",
        "price": 6.01,
        "pct": 1.52,
        "amount": 202100000.0,
        "turnover": 4.97,
        "vol_ratio": 4.05,
        "pe": 87.58,
        "pe_ttm": 61.69,
        "pb": 2.45,
        "total_cap": 3969000000.0,
        "float_cap": 6338000000.0,
        "main_net": null,
        "concepts": [
          "社会服务",
          "旅游及景区",
          "自然景区",
          "浙江板块",
          "最近多板",
          "昨日高振幅"
        ],
        "score": 81.12,
        "holder_num": 45991.0,
        "holder_change_ratio": -11.574474630367,
        "holder_avg_shares": 22929.4522841426,
        "holder_date": "2026-03-31"
      },
      {
        "code": "600376",
        "name": "首开股份",
        "price": 3.37,
        "pct": 4.01,
        "amount": 242880000.0,
        "turnover": 2.85,
        "vol_ratio": 2.42,
        "pe": -2.88,
        "pe_ttm": -1.38,
        "pb": 3.69,
        "total_cap": 8693000000.0,
        "float_cap": 8693000000.0,
        "main_net": null,
        "concepts": [
          "房地产",
          "房地产开发",
          "住宅开发",
          "北京板块",
          "破增发价股",
          "小盘价值"
        ],
        "score": 80.17,
        "holder_num": 145614.0,
        "holder_change_ratio": -23.515631565678,
        "holder_avg_shares": 17715.0908703833,
        "holder_date": "2026-03-31"
      },
      {
        "code": "002693",
        "name": "双成药业",
        "price": 9.15,
        "pct": 0.44,
        "amount": 209530000.0,
        "turnover": 5.52,
        "vol_ratio": 3.19,
        "pe": 275.1,
        "pe_ttm": 116.64,
        "pb": 9.12,
        "total_cap": 3760000000.0,
        "float_cap": 3794000000.0,
        "main_net": null,
        "concepts": [
          "医药生物",
          "化学制药",
          "化学制剂",
          "海南板块",
          "2025年报扭亏",
          "最近多板"
        ],
        "score": 79.81,
        "holder_num": 32225.0,
        "holder_change_ratio": -16.748475767283,
        "holder_avg_shares": 12868.5725368503,
        "holder_date": "2026-03-31"
      },
      {
        "code": "688538",
        "name": "和辉光电-U",
        "price": 2.59,
        "pct": 5.71,
        "amount": 490110000.0,
        "turnover": 3.31,
        "vol_ratio": 2.45,
        "pe": -19.03,
        "pe_ttm": -18.49,
        "pb": 4.71,
        "total_cap": 14897999999.999998,
        "float_cap": 35766000000.0,
        "main_net": null,
        "concepts": [
          "电子",
          "光学光电子",
          "面板",
          "上海板块",
          "破发股",
          "中盘股"
        ],
        "score": 79.06,
        "holder_num": 107703.0,
        "holder_change_ratio": -2.435864917748,
        "holder_avg_shares": 128217.762040055,
        "holder_date": "2026-03-31"
      },
      {
        "code": "600100",
        "name": "同方股份",
        "price": 6.83,
        "pct": 4.59,
        "amount": 234090000.0,
        "turnover": 1.03,
        "vol_ratio": 2.05,
        "pe": -31.18,
        "pe_ttm": 69.03,
        "pb": 1.46,
        "total_cap": 22883000000.0,
        "float_cap": 22883000000.0,
        "main_net": null,
        "concepts": [
          "计算机",
          "计算机设备",
          "其他计算机设备",
          "北京板块",
          "2025年报预增",
          "中盘成长"
        ],
        "score": 77.38,
        "holder_num": 153546.0,
        "holder_change_ratio": -7.5258067236,
        "holder_avg_shares": 21819.504988733,
        "holder_date": "2026-03-31"
      },
      {
        "code": "002146",
        "name": "荣盛发展",
        "price": 1.07,
        "pct": 2.88,
        "amount": 146270000.0,
        "turnover": 3.43,
        "vol_ratio": 2.44,
        "pe": -1.77,
        "pe_ttm": -0.51,
        "pb": 0.92,
        "total_cap": 4185000000.0,
        "float_cap": 4653000000.0,
        "main_net": null,
        "concepts": [
          "房地产",
          "房地产开发",
          "住宅开发",
          "河北板块",
          "破发股",
          "昨日高振幅"
        ],
        "score": 77.29,
        "holder_num": 135944.0,
        "holder_change_ratio": -12.060444536445,
        "holder_avg_shares": 31984.9633010651,
        "holder_date": "2026-03-31"
      },
      {
        "code": "000420",
        "name": "吉林化纤",
        "price": 4.06,
        "pct": -3.33,
        "amount": 329860000.0,
        "turnover": 3.32,
        "vol_ratio": 1.72,
        "pe": 91.59,
        "pe_ttm": 239.34,
        "pb": 2.25,
        "total_cap": 9980000000.0,
        "float_cap": 9983000000.0,
        "main_net": null,
        "concepts": [
          "基础化工",
          "化学纤维",
          "粘胶",
          "吉林板块",
          "小盘股",
          "昨日高振幅"
        ],
        "score": 76.64,
        "holder_num": 141307.0,
        "holder_change_ratio": -0.788457487889,
        "holder_avg_shares": 17400.8955182687,
        "holder_date": "2026-03-31"
      },
      {
        "code": "000404",
        "name": "长虹华意",
        "price": 7.74,
        "pct": -3.97,
        "amount": 184020000.0,
        "turnover": 3.42,
        "vol_ratio": 2.67,
        "pe": 11.67,
        "pe_ttm": 10.57,
        "pb": 1.28,
        "total_cap": 5362000000.0,
        "float_cap": 5387000000.0,
        "main_net": null,
        "concepts": [
          "家用电器",
          "家电零部件Ⅱ",
          "家电零部件Ⅲ",
          "江西板块",
          "价值股",
          "昨日高振幅"
        ],
        "score": 74.25,
        "holder_num": 30536.0,
        "holder_change_ratio": -0.647470310721,
        "holder_avg_shares": 22792.6375098245,
        "holder_date": "2026-03-31"
      },
      {
        "code": "300307",
        "name": "慈星股份",
        "price": 7.33,
        "pct": 1.66,
        "amount": 170630000.0,
        "turnover": 3.0,
        "vol_ratio": 1.51,
        "pe": 16.17,
        "pe_ttm": 52.39,
        "pb": 1.79,
        "total_cap": 5768000000.0,
        "float_cap": 5868000000.0,
        "main_net": null,
        "concepts": [
          "机械设备",
          "专用设备",
          "纺织服装设备",
          "浙江板块",
          "2025年报预减",
          "破发股"
        ],
        "score": 73.04,
        "holder_num": 44472.0,
        "holder_change_ratio": -3.085774058577,
        "holder_avg_shares": 18001.2991545242,
        "holder_date": "2026-03-31"
      },
      {
        "code": "002277",
        "name": "友阿股份",
        "price": 5.91,
        "pct": -5.14,
        "amount": 199770000.0,
        "turnover": 2.38,
        "vol_ratio": 2.34,
        "pe": 48.59,
        "pe_ttm": -25.06,
        "pb": 1.29,
        "total_cap": 8240000000.000001,
        "float_cap": 8240000000.000001,
        "main_net": null,
        "concepts": [
          "商贸零售",
          "一般零售",
          "百货",
          "湖南板块",
          "最近多板",
          "昨日高振幅"
        ],
        "score": 69.45,
        "holder_num": 51657.0,
        "holder_change_ratio": -2.78342366757,
        "holder_avg_shares": 26989.0392395997,
        "holder_date": "2026-06-19"
      },
      {
        "code": "600273",
        "name": "嘉化能源",
        "price": 6.47,
        "pct": -3.43,
        "amount": 101290000.0,
        "turnover": 1.19,
        "vol_ratio": 1.88,
        "pe": 20.52,
        "pe_ttm": 10.4,
        "pb": 0.86,
        "total_cap": 8484000000.0,
        "float_cap": 8484000000.0,
        "main_net": null,
        "concepts": [
          "基础化工",
          "化学制品",
          "其他化学制品",
          "浙江板块",
          "小盘价值",
          "小盘股"
        ],
        "score": 67.83,
        "holder_num": 33907.0,
        "holder_change_ratio": -13.473856125756,
        "holder_avg_shares": 40017.6813637302,
        "holder_date": "2026-03-31"
      },
      {
        "code": "600398",
        "name": "海澜之家",
        "price": 5.16,
        "pct": -3.37,
        "amount": 136280000.0,
        "turnover": 0.55,
        "vol_ratio": 2.06,
        "pe": 6.53,
        "pe_ttm": 11.37,
        "pb": 1.43,
        "total_cap": 24782000000.0,
        "float_cap": 24782000000.0,
        "main_net": null,
        "concepts": [
          "纺织服饰",
          "服装家纺",
          "非运动服装",
          "江苏板块",
          "消费风格",
          "中盘价值"
        ],
        "score": 66.62,
        "holder_num": 63064.0,
        "holder_change_ratio": -3.915653472286,
        "holder_avg_shares": 76157.0832170494,
        "holder_date": "2026-03-31"
      },
      {
        "code": "600207",
        "name": "安彩高科",
        "price": 5.82,
        "pct": 5.63,
        "amount": 179370000.0,
        "turnover": 2.86,
        "vol_ratio": 1.76,
        "pe": -10.71,
        "pe_ttm": -8.26,
        "pb": 3.38,
        "total_cap": 6340000000.0,
        "float_cap": 6340000000.0,
        "main_net": null,
        "concepts": [
          "电力设备",
          "光伏设备",
          "光伏辅材",
          "河南板块",
          "破发股",
          "昨日高振幅"
        ],
        "score": 66.46,
        "holder_num": 45000.0,
        "holder_change_ratio": -8.163265306122,
        "holder_avg_shares": 24206.9456444444,
        "holder_date": "2026-06-10"
      },
      {
        "code": "002036",
        "name": "联创电子",
        "price": 7.57,
        "pct": 10.03,
        "amount": 282040000.0,
        "turnover": 3.61,
        "vol_ratio": 1.58,
        "pe": -20.68,
        "pe_ttm": -7.2,
        "pb": 8.29,
        "total_cap": 7990000000.000001,
        "float_cap": 8006000000.0,
        "main_net": null,
        "concepts": [
          "电子",
          "光学光电子",
          "光学元件",
          "江西板块",
          "小盘价值",
          "小盘股"
        ],
        "score": 66.34,
        "holder_num": 134151.0,
        "holder_change_ratio": -1.726638731796,
        "holder_avg_shares": 7883.63900380914,
        "holder_date": "2026-06-18"
      },
      {
        "code": "603336",
        "name": "宏辉果蔬",
        "price": 8.06,
        "pct": -1.71,
        "amount": 181840000.0,
        "turnover": 3.66,
        "vol_ratio": 2.24,
        "pe": 407.65,
        "pe_ttm": 300.68,
        "pb": 3.41,
        "total_cap": 4906000000.0,
        "float_cap": 4906000000.0,
        "main_net": null,
        "concepts": [
          "农林牧渔",
          "种植业",
          "其他种植业",
          "广东板块",
          "最近多板",
          "昨日高振幅"
        ],
        "score": 65.2,
        "holder_num": 20460.0,
        "holder_change_ratio": -8.468661924574,
        "holder_avg_shares": 29751.6590909091,
        "holder_date": "2026-03-31"
      },
      {
        "code": "603313",
        "name": "梦百合",
        "price": 5.79,
        "pct": -6.91,
        "amount": 133970000.0,
        "turnover": 4.03,
        "vol_ratio": 1.62,
        "pe": -21.67,
        "pe_ttm": -30.98,
        "pb": 0.97,
        "total_cap": 3304000000.0,
        "float_cap": 3304000000.0,
        "main_net": null,
        "concepts": [
          "轻工制造",
          "家居用品",
          "成品家居",
          "江苏板块",
          "破增发价股",
          "破发股"
        ],
        "score": 64.67,
        "holder_num": 24733.0,
        "holder_change_ratio": -3.672690450226,
        "holder_avg_shares": 23069.8615210448,
        "holder_date": "2026-03-31"
      },
      {
        "code": "300393",
        "name": "中来股份",
        "price": 7.38,
        "pct": 4.68,
        "amount": 199570000.0,
        "turnover": 2.83,
        "vol_ratio": 2.0,
        "pe": -8.01,
        "pe_ttm": -5.4,
        "pb": 4.54,
        "total_cap": 7055000000.0,
        "float_cap": 8041000000.0,
        "main_net": null,
        "concepts": [
          "电力设备",
          "光伏设备",
          "光伏电池组件",
          "江苏板块",
          "创业板综",
          "深股通"
        ],
        "score": 64.04,
        "holder_num": 57672.0,
        "holder_change_ratio": -6.673571104926,
        "holder_avg_shares": 18893.5247260369,
        "holder_date": "2026-03-31"
      },
      {
        "code": "600810",
        "name": "神马股份",
        "price": 6.14,
        "pct": -7.53,
        "amount": 115120000.0,
        "turnover": 1.7,
        "vol_ratio": 1.51,
        "pe": -53.44,
        "pe_ttm": -38.34,
        "pb": 0.97,
        "total_cap": 6636000000.0,
        "float_cap": 6695999999.999999,
        "main_net": null,
        "concepts": [
          "基础化工",
          "化学纤维",
          "锦纶",
          "河南板块",
          "昨日高振幅",
          "沪股通"
        ],
        "score": 62.75,
        "holder_num": 49435.0,
        "holder_change_ratio": -21.239205939521,
        "holder_avg_shares": 22479.4798219885,
        "holder_date": "2026-03-31"
      },
      {
        "code": "002114",
        "name": "罗平锌电",
        "price": 7.23,
        "pct": -1.77,
        "amount": 133440000.0,
        "turnover": 5.75,
        "vol_ratio": 1.51,
        "pe": -14.81,
        "pe_ttm": -13.56,
        "pb": 3.24,
        "total_cap": 2338000000.0,
        "float_cap": 2338000000.0,
        "main_net": null,
        "concepts": [
          "有色金属",
          "工业金属",
          "铅锌",
          "云南板块",
          "破增发价股",
          "昨日高振幅"
        ],
        "score": 62.53,
        "holder_num": 53007.0,
        "holder_change_ratio": -1.625744669005,
        "holder_avg_shares": 6100.99169920954,
        "holder_date": "2026-03-31"
      },
      {
        "code": "688602",
        "name": "康鹏科技",
        "price": 7.75,
        "pct": -3.25,
        "amount": 90930000.0,
        "turnover": 4.46,
        "vol_ratio": 1.64,
        "pe": -79.96,
        "pe_ttm": -37.47,
        "pb": 1.48,
        "total_cap": 2012000000.0,
        "float_cap": 4025000000.0,
        "main_net": null,
        "concepts": [
          "医药生物",
          "化学制药",
          "化学制剂",
          "上海板块",
          "破发股",
          "融资融券"
        ],
        "score": 61.68,
        "holder_num": 13785.0,
        "holder_change_ratio": -4.582266214439,
        "holder_avg_shares": 37676.8226332971,
        "holder_date": "2026-03-31"
      },
      {
        "code": "000017",
        "name": "深中华A",
        "price": 5.86,
        "pct": 5.4,
        "amount": 129200000.0,
        "turnover": 5.0,
        "vol_ratio": 3.82,
        "pe": 165.1,
        "pe_ttm": 97.69,
        "pb": 10.35,
        "total_cap": 2583000000.0,
        "float_cap": 4039000000.0,
        "main_net": null,
        "concepts": [
          "纺织服饰",
          "饰品",
          "钟表珠宝",
          "广东板块",
          "2025年报预增",
          "最近多板"
        ],
        "score": 61.51,
        "holder_num": 21358.0,
        "holder_change_ratio": -10.800200467758,
        "holder_avg_shares": 14186.1405562319,
        "holder_date": "2013-06-30"
      },
      {
        "code": "002615",
        "name": "哈尔斯",
        "price": 6.37,
        "pct": 1.59,
        "amount": 102510000.0,
        "turnover": 5.24,
        "vol_ratio": 2.46,
        "pe": 737.97,
        "pe_ttm": 118.98,
        "pb": 1.5,
        "total_cap": 1925000000.0,
        "float_cap": 3565999999.9999995,
        "main_net": null,
        "concepts": [
          "轻工制造",
          "家居用品",
          "其他家居用品",
          "浙江板块",
          "2025年报预减",
          "破增发价股"
        ],
        "score": 60.67,
        "holder_num": 21011.0,
        "holder_change_ratio": -21.011278195489,
        "holder_avg_shares": 22191.6011612965,
        "holder_date": "2026-03-31"
      },
      {
        "code": "002727",
        "name": "一心堂",
        "price": 9.52,
        "pct": -4.99,
        "amount": 68370000.0,
        "turnover": 1.79,
        "vol_ratio": 1.67,
        "pe": 7.93,
        "pe_ttm": 19.97,
        "pb": 0.76,
        "total_cap": 3740999999.9999995,
        "float_cap": 5575000000.0,
        "main_net": null,
        "concepts": [
          "医药生物",
          "医药商业",
          "线下药店",
          "云南板块",
          "2025年报预增",
          "破增发价股"
        ],
        "score": 59.43,
        "holder_num": 41801.0,
        "holder_change_ratio": -6.039830965654,
        "holder_avg_shares": 14009.3329106959,
        "holder_date": "2026-03-31"
      },
      {
        "code": "002591",
        "name": "恒大高新",
        "price": 6.16,
        "pct": 0.33,
        "amount": 68800000.0,
        "turnover": 4.96,
        "vol_ratio": 2.0,
        "pe": 74.36,
        "pe_ttm": -84.98,
        "pb": 2.89,
        "total_cap": 1377000000.0,
        "float_cap": 1848999999.9999998,
        "main_net": null,
        "concepts": [
          "基础化工",
          "化学制品",
          "其他化学制品",
          "江西板块",
          "破增发价股",
          "机构重仓"
        ],
        "score": 59.41,
        "holder_num": 22245.0,
        "holder_change_ratio": -27.663241415193,
        "holder_avg_shares": 13495.1442571364,
        "holder_date": "2026-03-31"
      },
      {
        "code": "000863",
        "name": "三湘印象",
        "price": 4.17,
        "pct": 2.71,
        "amount": 81920000.0,
        "turnover": 1.68,
        "vol_ratio": 1.59,
        "pe": -242.43,
        "pe_ttm": -31.88,
        "pb": 1.13,
        "total_cap": 4851000000.0,
        "float_cap": 4924000000.0,
        "main_net": null,
        "concepts": [
          "房地产",
          "房地产开发",
          "住宅开发",
          "上海板块",
          "深股通",
          "融资融券"
        ],
        "score": 59.38,
        "holder_num": 25253.0,
        "holder_change_ratio": -32.926958831341,
        "holder_avg_shares": 46754.8235853166,
        "holder_date": "2026-03-31"
      },
      {
        "code": "600827",
        "name": "百联股份",
        "price": 7.47,
        "pct": -2.86,
        "amount": 61670000.0,
        "turnover": 0.51,
        "vol_ratio": 1.84,
        "pe": 4.21,
        "pe_ttm": 10.83,
        "pb": 0.65,
        "total_cap": 11985000000.0,
        "float_cap": 13328000000.0,
        "main_net": null,
        "concepts": [
          "商贸零售",
          "一般零售",
          "多业态零售",
          "上海板块",
          "消费风格",
          "2025年报预减"
        ],
        "score": 58.27,
        "holder_num": 72733.0,
        "holder_change_ratio": -5.596729184243,
        "holder_avg_shares": 22059.4492183741,
        "holder_date": "2022-09-30"
      },
      {
        "code": "002053",
        "name": "云南能投",
        "price": 9.83,
        "pct": 9.96,
        "amount": 143650000.0,
        "turnover": 1.63,
        "vol_ratio": 2.38,
        "pe": 10.98,
        "pe_ttm": 40.9,
        "pb": 1.21,
        "total_cap": 9051000000.0,
        "float_cap": 9051000000.0,
        "main_net": null,
        "concepts": [
          "公用事业",
          "电力",
          "风力发电",
          "云南板块",
          "2025年报预减",
          "破增发价股"
        ],
        "score": 57.89,
        "holder_num": 28665.0,
        "holder_change_ratio": -0.371889336855,
        "holder_avg_shares": 32120.33713588,
        "holder_date": "2026-06-10"
      },
      {
        "code": "600076",
        "name": "康欣新材",
        "price": 3.31,
        "pct": 9.97,
        "amount": 133010000.0,
        "turnover": 3.09,
        "vol_ratio": 1.93,
        "pe": -21.44,
        "pe_ttm": -11.38,
        "pb": 1.25,
        "total_cap": 4450000000.0,
        "float_cap": 4450000000.0,
        "main_net": null,
        "concepts": [
          "轻工制造",
          "包装印刷",
          "综合包装",
          "山东板块",
          "昨日高振幅",
          "融资融券"
        ],
        "score": 57.61,
        "holder_num": 48654.0,
        "holder_change_ratio": -3.447044115021,
        "holder_avg_shares": 27634.7960496568,
        "holder_date": "2026-06-10"
      },
      {
        "code": "002091",
        "name": "江苏国泰",
        "price": 7.25,
        "pct": 2.11,
        "amount": 61630000.0,
        "turnover": 0.53,
        "vol_ratio": 1.53,
        "pe": 13.93,
        "pe_ttm": 9.34,
        "pb": 0.76,
        "total_cap": 11587000000.0,
        "float_cap": 11801000000.0,
        "main_net": null,
        "concepts": [
          "商贸零售",
          "贸易Ⅱ",
          "贸易Ⅲ",
          "江苏板块",
          "小盘价值",
          "小盘股"
        ],
        "score": 57.32,
        "holder_num": 54758.0,
        "holder_change_ratio": -6.431769249171,
        "holder_avg_shares": 29725.6194528653,
        "holder_date": "2026-03-31"
      },
      {
        "code": "002863",
        "name": "今飞凯达",
        "price": 4.22,
        "pct": -1.17,
        "amount": 35720000.0,
        "turnover": 1.41,
        "vol_ratio": 1.52,
        "pe": 21.51,
        "pe_ttm": 39.54,
        "pb": 0.9,
        "total_cap": 2530000000.0,
        "float_cap": 2530000000.0,
        "main_net": null,
        "concepts": [
          "汽车",
          "汽车零部件",
          "轮胎轮毂",
          "浙江板块",
          "破增发价股",
          "破净股"
        ],
        "score": 57.08,
        "holder_num": 28906.0,
        "holder_change_ratio": -11.09402392889,
        "holder_avg_shares": 20739.0698816855,
        "holder_date": "2026-03-31"
      },
      {
        "code": "000829",
        "name": "天音控股",
        "price": 7.8,
        "pct": 10.01,
        "amount": 151350000.0,
        "turnover": 1.95,
        "vol_ratio": 1.78,
        "pe": -78.76,
        "pe_ttm": -434.79,
        "pb": 2.76,
        "total_cap": 7988000000.0,
        "float_cap": 7995999999.999999,
        "main_net": null,
        "concepts": [
          "商贸零售",
          "专业连锁Ⅱ",
          "专业连锁Ⅲ",
          "江西板块",
          "内贸流通",
          "标准普尔"
        ],
        "score": 56.78,
        "holder_num": 63503.0,
        "holder_change_ratio": -7.076486340157,
        "holder_avg_shares": 16142.551344031,
        "holder_date": "2026-05-10"
      },
      {
        "code": "002887",
        "name": "绿茵生态",
        "price": 9.98,
        "pct": 1.63,
        "amount": 41680000.0,
        "turnover": 1.96,
        "vol_ratio": 1.51,
        "pe": 18.96,
        "pe_ttm": 22.62,
        "pb": 1.33,
        "total_cap": 2168000000.0,
        "float_cap": 3054000000.0,
        "main_net": null,
        "concepts": [
          "环保",
          "环境治理",
          "综合环境治理",
          "天津板块",
          "机构重仓",
          "QFII重仓"
        ],
        "score": 55.81,
        "holder_num": 13388.0,
        "holder_change_ratio": -7.967278476662,
        "holder_avg_shares": 22855.3660740962,
        "holder_date": "2026-03-31"
      },
      {
        "code": "002676",
        "name": "顺威股份",
        "price": 5.01,
        "pct": 3.3,
        "amount": 75560000.0,
        "turnover": 2.1,
        "vol_ratio": 1.81,
        "pe": 34.33,
        "pe_ttm": 43.55,
        "pb": 2.7,
        "total_cap": 3607000000.0,
        "float_cap": 3607000000.0,
        "main_net": null,
        "concepts": [
          "家用电器",
          "家电零部件Ⅱ",
          "家电零部件Ⅲ",
          "广东板块",
          "深股通",
          "新能源车"
        ],
        "score": 55.64,
        "holder_num": 38764.0,
        "holder_change_ratio": -11.932024718284,
        "holder_avg_shares": 18573.9345784749,
        "holder_date": "2026-03-31"
      },
      {
        "code": "000650",
        "name": "仁和药业",
        "price": 5.03,
        "pct": -0.98,
        "amount": 69320000.0,
        "turnover": 1.04,
        "vol_ratio": 1.73,
        "pe": 12.54,
        "pe_ttm": 19.07,
        "pb": 1.09,
        "total_cap": 6697000000.0,
        "float_cap": 7042000000.0,
        "main_net": null,
        "concepts": [
          "医药生物",
          "中药Ⅱ",
          "中药Ⅲ",
          "江西板块",
          "标准普尔",
          "富时罗素"
        ],
        "score": 55.29,
        "holder_num": 85700.0,
        "holder_change_ratio": -4.352678571429,
        "holder_avg_shares": 16335.335285881,
        "holder_date": "2026-06-18"
      },
      {
        "code": "000090",
        "name": "天健集团",
        "price": 3.0,
        "pct": -3.54,
        "amount": 46210000.0,
        "turnover": 0.82,
        "vol_ratio": 1.51,
        "pe": -60.11,
        "pe_ttm": 35.08,
        "pb": 0.5,
        "total_cap": 5605000000.0,
        "float_cap": 5606000000.0,
        "main_net": null,
        "concepts": [
          "房地产",
          "房地产开发",
          "住宅开发",
          "广东板块",
          "2025年报预减",
          "红利股"
        ],
        "score": 55.12,
        "holder_num": 39728.0,
        "holder_change_ratio": -10.781737743942,
        "holder_avg_shares": 47033.4634011277,
        "holder_date": "2026-03-31"
      },
      {
        "code": "600966",
        "name": "博汇纸业",
        "price": 4.75,
        "pct": -5.0,
        "amount": 53460000.0,
        "turnover": 0.83,
        "vol_ratio": 1.83,
        "pe": 28.67,
        "pe_ttm": 40.32,
        "pb": 0.85,
        "total_cap": 6350000000.0,
        "float_cap": 6350000000.0,
        "main_net": null,
        "concepts": [
          "轻工制造",
          "造纸",
          "大宗用纸",
          "山东板块",
          "昨日高振幅",
          "破净股"
        ],
        "score": 54.87,
        "holder_num": 41508.0,
        "holder_change_ratio": -9.674892283588,
        "holder_avg_shares": 32206.9068131445,
        "holder_date": "2026-03-31"
      },
      {
        "code": "603707",
        "name": "健友股份",
        "price": 7.09,
        "pct": -2.34,
        "amount": 82490000.0,
        "turnover": 0.71,
        "vol_ratio": 1.65,
        "pe": 32.17,
        "pe_ttm": 19.55,
        "pb": 1.69,
        "total_cap": 11455000000.0,
        "float_cap": 11455000000.0,
        "main_net": null,
        "concepts": [
          "医药生物",
          "化学制药",
          "化学制剂",
          "江苏板块",
          "小盘股",
          "昨日高振幅"
        ],
        "score": 53.89,
        "holder_num": 35693.0,
        "holder_change_ratio": -6.307748845023,
        "holder_avg_shares": 45265.0054352394,
        "holder_date": "2026-03-31"
      },
      {
        "code": "000536",
        "name": "华映科技",
        "price": 3.25,
        "pct": 5.18,
        "amount": 220800000.0,
        "turnover": 2.44,
        "vol_ratio": 2.19,
        "pe": -10.12,
        "pe_ttm": -8.81,
        "pb": 10.7,
        "total_cap": 8980000000.0,
        "float_cap": 8990000000.0,
        "main_net": null,
        "concepts": [
          "电子",
          "光学光电子",
          "面板",
          "福建板块",
          "小盘股",
          "标准普尔"
        ],
        "score": 53.3,
        "holder_num": 216480.0,
        "holder_change_ratio": -0.162337662338,
        "holder_avg_shares": 12777.3133915373,
        "holder_date": "2026-06-18"
      },
      {
        "code": "600548",
        "name": "深高速",
        "price": 8.1,
        "pct": -2.29,
        "amount": 17380000.0,
        "turnover": 0.12,
        "vol_ratio": 1.97,
        "pe": 10.09,
        "pe_ttm": 17.41,
        "pb": 0.88,
        "total_cap": 13887000000.0,
        "float_cap": 20557000000.0,
        "main_net": null,
        "concepts": [
          "交通运输",
          "铁路公路",
          "高速公路",
          "广东板块",
          "破增发价股",
          "小盘价值"
        ],
        "score": 53.16,
        "holder_num": 22604.0,
        "holder_change_ratio": -7.227580545865,
        "holder_avg_shares": 79205.2790214121,
        "holder_date": "2026-03-31"
      },
      {
        "code": "600461",
        "name": "洪城环境",
        "price": 9.0,
        "pct": -2.49,
        "amount": 63930000.0,
        "turnover": 0.55,
        "vol_ratio": 1.63,
        "pe": 9.14,
        "pe_ttm": 9.81,
        "pb": 1.13,
        "total_cap": 11557000000.0,
        "float_cap": 11557000000.0,
        "main_net": null,
        "concepts": [
          "环保",
          "环境治理",
          "水务及水治理",
          "江西板块",
          "小盘价值",
          "小盘股"
        ],
        "score": 52.74,
        "holder_num": 19066.0,
        "holder_change_ratio": -3.731380964403,
        "holder_avg_shares": 67353.1724535823,
        "holder_date": "2026-03-31"
      },
      {
        "code": "603366",
        "name": "日出东方",
        "price": 7.27,
        "pct": 9.98,
        "amount": 97390000.0,
        "turnover": 1.66,
        "vol_ratio": 1.83,
        "pe": -37.2,
        "pe_ttm": 32.52,
        "pb": 1.39,
        "total_cap": 5911000000.0,
        "float_cap": 5911000000.0,
        "main_net": null,
        "concepts": [
          "家用电器",
          "厨卫电器",
          "卫浴电器",
          "江苏板块",
          "破发股",
          "昨日高振幅"
        ],
        "score": 52.62,
        "holder_num": 82960.0,
        "holder_change_ratio": -5.624317437204,
        "holder_avg_shares": 9800.48337753134,
        "holder_date": "2026-03-31"
      },
      {
        "code": "300071",
        "name": "福石控股",
        "price": 3.51,
        "pct": 3.24,
        "amount": 108090000.0,
        "turnover": 3.25,
        "vol_ratio": 1.92,
        "pe": -1278.6,
        "pe_ttm": -29.79,
        "pb": 21.02,
        "total_cap": 3318000000.0,
        "float_cap": 3383000000.0,
        "main_net": null,
        "concepts": [
          "传媒",
          "广告营销",
          "营销代理",
          "北京板块",
          "创业板综",
          "深股通"
        ],
        "score": 52.38,
        "holder_num": 72629.0,
        "holder_change_ratio": -11.925348338043,
        "holder_avg_shares": 13271.3425215823,
        "holder_date": "2026-03-31"
      },
      {
        "code": "002427",
        "name": "尤夫股份",
        "price": 4.97,
        "pct": -5.69,
        "amount": 168460000.0,
        "turnover": 3.43,
        "vol_ratio": 1.64,
        "pe": -61.05,
        "pe_ttm": 385.44,
        "pb": 5.17,
        "total_cap": 4893000000.0,
        "float_cap": 4898000000.0,
        "main_net": null,
        "concepts": [
          "基础化工",
          "化学纤维",
          "涤纶",
          "浙江板块",
          "2025年报扭亏",
          "破增发价股"
        ],
        "score": 52.2,
        "holder_num": 56181.0,
        "holder_change_ratio": -3.699069233274,
        "holder_avg_shares": 17540.3210516011,
        "holder_date": "2026-03-31"
      },
      {
        "code": "600156",
        "name": "华升股份",
        "price": 8.26,
        "pct": 2.61,
        "amount": 122170000.0,
        "turnover": 3.69,
        "vol_ratio": 1.88,
        "pe": -143.4,
        "pe_ttm": -116.52,
        "pb": 9.09,
        "total_cap": 3321000000.0,
        "float_cap": 3321000000.0,
        "main_net": null,
        "concepts": [
          "纺织服饰",
          "纺织制造",
          "其他纺织",
          "湖南板块",
          "并购重组概念",
          "液冷概念"
        ],
        "score": 51.98,
        "holder_num": 24636.0,
        "holder_change_ratio": -6.784214310038,
        "holder_avg_shares": 16322.0775288196,
        "holder_date": "2026-03-31"
      },
      {
        "code": "000159",
        "name": "国际实业",
        "price": 5.34,
        "pct": 0.95,
        "amount": 66370000.0,
        "turnover": 2.54,
        "vol_ratio": 1.7,
        "pe": 87.98,
        "pe_ttm": 69.95,
        "pb": 1.25,
        "total_cap": 2567000000.0,
        "float_cap": 2567000000.0,
        "main_net": null,
        "concepts": [
          "石油石化",
          "炼化及贸易",
          "油品石化贸易",
          "新疆板块",
          "2025年报扭亏",
          "反内卷概念"
        ],
        "score": 50.93,
        "holder_num": 42533.0,
        "holder_change_ratio": -8.418922119587,
        "holder_avg_shares": 11301.4833893683,
        "holder_date": "2026-05-29"
      },
      {
        "code": "002548",
        "name": "金新农",
        "price": 3.68,
        "pct": 1.66,
        "amount": 79360000.0,
        "turnover": 2.66,
        "vol_ratio": 1.52,
        "pe": -4.13,
        "pe_ttm": -6.75,
        "pb": 2.91,
        "total_cap": 2960000000.0,
        "float_cap": 3048000000.0,
        "main_net": null,
        "concepts": [
          "农林牧渔",
          "饲料",
          "畜禽饲料",
          "广东板块",
          "破增发价股",
          "破发股"
        ],
        "score": 50.33,
        "holder_num": 48916.0,
        "holder_change_ratio": -6.38265296358,
        "holder_avg_shares": 16930.5269850356,
        "holder_date": "2026-05-10"
      },
      {
        "code": "002403",
        "name": "爱仕达",
        "price": 8.9,
        "pct": 4.34,
        "amount": 53100000.0,
        "turnover": 2.02,
        "vol_ratio": 2.31,
        "pe": -72.3,
        "pe_ttm": -12.99,
        "pb": 2.19,
        "total_cap": 2645000000.0,
        "float_cap": 3032000000.0,
        "main_net": null,
        "concepts": [
          "家用电器",
          "小家电",
          "厨房小家电",
          "浙江板块",
          "破发股",
          "跨境电商"
        ],
        "score": 49.99,
        "holder_num": 37125.0,
        "holder_change_ratio": -13.224879040741,
        "holder_avg_shares": 9175.44993939394,
        "holder_date": "2026-03-31"
      },
      {
        "code": "002688",
        "name": "金河生物",
        "price": 4.62,
        "pct": -4.15,
        "amount": 37690000.0,
        "turnover": 1.08,
        "vol_ratio": 1.76,
        "pe": 14.27,
        "pe_ttm": 91.78,
        "pb": 1.61,
        "total_cap": 3453000000.0,
        "float_cap": 3554999999.9999995,
        "main_net": null,
        "concepts": [
          "农林牧渔",
          "动物保健Ⅱ",
          "动物保健Ⅲ",
          "内蒙古",
          "2025年报预减",
          "深股通"
        ],
        "score": 49.09,
        "holder_num": 47987.0,
        "holder_change_ratio": -7.489589759408,
        "holder_avg_shares": 16035.6846229187,
        "holder_date": "2026-03-31"
      },
      {
        "code": "601005",
        "name": "重庆钢铁",
        "price": 1.16,
        "pct": 0.87,
        "amount": 88540000.0,
        "turnover": 0.91,
        "vol_ratio": 1.81,
        "pe": -13.99,
        "pe_ttm": -3.98,
        "pb": 0.76,
        "total_cap": 9644000000.0,
        "float_cap": 11147000000.0,
        "main_net": null,
        "concepts": [
          "钢铁",
          "普钢",
          "板材",
          "重庆板块",
          "破增发价股",
          "破发股"
        ],
        "score": 48.77,
        "holder_num": 167136.0,
        "holder_change_ratio": -0.77121738356,
        "holder_avg_shares": 50141.6515113441,
        "holder_date": "2024-02-08"
      },
      {
        "code": "000036",
        "name": "华联控股",
        "price": 4.34,
        "pct": -2.91,
        "amount": 88400000.0,
        "turnover": 1.43,
        "vol_ratio": 1.7,
        "pe": 58.5,
        "pe_ttm": 67.36,
        "pb": 1.18,
        "total_cap": 6089000000.0,
        "float_cap": 6093000000.0,
        "main_net": null,
        "concepts": [
          "房地产",
          "房地产开发",
          "住宅开发",
          "广东板块",
          "标准普尔",
          "富时罗素"
        ],
        "score": 48.0,
        "holder_num": 46139.0,
        "holder_change_ratio": -3.325231529984,
        "holder_avg_shares": 30425.8593597607,
        "holder_date": "2026-05-20"
      },
      {
        "code": "605577",
        "name": "龙版传媒",
        "price": 8.73,
        "pct": -2.68,
        "amount": 21450000.0,
        "turnover": 0.55,
        "vol_ratio": 1.72,
        "pe": 7.87,
        "pe_ttm": 16.26,
        "pb": 0.96,
        "total_cap": 3879999999.9999995,
        "float_cap": 3879999999.9999995,
        "main_net": null,
        "concepts": [
          "传媒",
          "出版",
          "教育出版",
          "黑龙江",
          "沪股通",
          "央国企改革"
        ],
        "score": 47.44,
        "holder_num": 17008.0,
        "holder_change_ratio": -6.2558562531,
        "holder_avg_shares": 26131.4937088429,
        "holder_date": "2026-03-31"
      },
      {
        "code": "601599",
        "name": "浙文影业",
        "price": 2.76,
        "pct": -2.13,
        "amount": 35040000.0,
        "turnover": 1.08,
        "vol_ratio": 1.62,
        "pe": 44.77,
        "pe_ttm": 28.75,
        "pb": 2.09,
        "total_cap": 3203000000.0,
        "float_cap": 3203000000.0,
        "main_net": null,
        "concepts": [
          "纺织服饰",
          "纺织制造",
          "其他纺织",
          "浙江板块",
          "破发股",
          "低价股"
        ],
        "score": 46.3,
        "holder_num": 47198.0,
        "holder_change_ratio": -18.451198230731,
        "holder_avg_shares": 24588.8057332938,
        "holder_date": "2026-03-31"
      },
      {
        "code": "600167",
        "name": "联美控股",
        "price": 5.5,
        "pct": 2.61,
        "amount": 37560000.0,
        "turnover": 0.3,
        "vol_ratio": 1.82,
        "pe": 5.84,
        "pe_ttm": 20.72,
        "pb": 1.04,
        "total_cap": 12446000000.0,
        "float_cap": 12446000000.0,
        "main_net": null,
        "concepts": [
          "公用事业",
          "电力",
          "热力服务",
          "辽宁板块",
          "小盘价值",
          "小盘股"
        ],
        "score": 46.2,
        "holder_num": 39837.0,
        "holder_change_ratio": -2.036149022501,
        "holder_avg_shares": 56802.4816878781,
        "holder_date": "2026-03-31"
      },
      {
        "code": "300388",
        "name": "节能国祯",
        "price": 6.13,
        "pct": -2.39,
        "amount": 34260000.0,
        "turnover": 0.81,
        "vol_ratio": 2.01,
        "pe": 11.59,
        "pe_ttm": 11.04,
        "pb": 0.87,
        "total_cap": 4175000000.0,
        "float_cap": 4175000000.0,
        "main_net": null,
        "concepts": [
          "环保",
          "环境治理",
          "水务及水治理",
          "安徽板块",
          "破增发价股",
          "破净股"
        ],
        "score": 46.04,
        "holder_num": 20622.0,
        "holder_change_ratio": -3.25577031338,
        "holder_avg_shares": 33025.0330229852,
        "holder_date": "2026-03-31"
      },
      {
        "code": "002644",
        "name": "佛慈制药",
        "price": 6.71,
        "pct": -6.55,
        "amount": 51680000.0,
        "turnover": 1.49,
        "vol_ratio": 3.8,
        "pe": 37.8,
        "pe_ttm": 65.28,
        "pb": 1.87,
        "total_cap": 3427000000.0000005,
        "float_cap": 3427000000.0000005,
        "main_net": null,
        "concepts": [
          "医药生物",
          "中药Ⅱ",
          "中药Ⅲ",
          "甘肃板块",
          "破增发价股",
          "病原体防治"
        ],
        "score": 45.67,
        "holder_num": 32491.0,
        "holder_change_ratio": -7.295708742296,
        "holder_avg_shares": 15716.8754424302,
        "holder_date": "2026-03-31"
      },
      {
        "code": "001217",
        "name": "华尔泰",
        "price": 8.36,
        "pct": -2.34,
        "amount": 23030000.0,
        "turnover": 0.83,
        "vol_ratio": 1.61,
        "pe": -47.53,
        "pe_ttm": -45.43,
        "pb": 1.29,
        "total_cap": 2744000000.0,
        "float_cap": 2774000000.0,
        "main_net": null,
        "concepts": [
          "基础化工",
          "化学原料",
          "其他化学原料",
          "安徽板块",
          "破发股",
          "2025三季报预减"
        ],
        "score": 45.32,
        "holder_num": 21599.0,
        "holder_change_ratio": -16.830958798614,
        "holder_avg_shares": 15365.0631973702,
        "holder_date": "2026-03-31"
      },
      {
        "code": "603333",
        "name": "福华尚纬",
        "price": 7.71,
        "pct": 2.94,
        "amount": 106290000.0,
        "turnover": 2.27,
        "vol_ratio": 1.96,
        "pe": 2186.72,
        "pe_ttm": -148.58,
        "pb": 2.35,
        "total_cap": 4792000000.0,
        "float_cap": 4792000000.0,
        "main_net": null,
        "concepts": [
          "电力设备",
          "电网设备",
          "线缆部件及其他",
          "四川板块",
          "微利股",
          "专精特新"
        ],
        "score": 44.75,
        "holder_num": 26556.0,
        "holder_change_ratio": -7.202012789601,
        "holder_avg_shares": 23404.4127880705,
        "holder_date": "2026-03-31"
      },
      {
        "code": "300654",
        "name": "世纪天鸿",
        "price": 9.78,
        "pct": 4.94,
        "amount": 121890000.0,
        "turnover": 3.55,
        "vol_ratio": 1.82,
        "pe": 164.07,
        "pe_ttm": 142.12,
        "pb": 4.26,
        "total_cap": 3449000000.0,
        "float_cap": 3581000000.0,
        "main_net": null,
        "concepts": [
          "传媒",
          "出版",
          "教育出版",
          "山东板块",
          "创业板综",
          "机构重仓"
        ],
        "score": 44.44,
        "holder_num": 21046.0,
        "holder_change_ratio": -3.174457121826,
        "holder_avg_shares": 17396.4103392569,
        "holder_date": "2026-06-18"
      },
      {
        "code": "300605",
        "name": "恒锋信息",
        "price": 9.35,
        "pct": 2.52,
        "amount": 51450000.0,
        "turnover": 4.37,
        "vol_ratio": 1.63,
        "pe": -27.98,
        "pe_ttm": -40.07,
        "pb": 3.54,
        "total_cap": 1182000000.0,
        "float_cap": 1544000000.0,
        "main_net": null,
        "concepts": [
          "计算机",
          "软件开发",
          "垂直应用软件",
          "福建板块",
          "创业板综",
          "转债标的"
        ],
        "score": 44.14,
        "holder_num": 17080.0,
        "holder_change_ratio": -3.158133469411,
        "holder_avg_shares": 9668.82581967213,
        "holder_date": "2026-04-10"
      },
      {
        "code": "000498",
        "name": "山东路桥",
        "price": 4.73,
        "pct": -1.87,
        "amount": 22870000.0,
        "turnover": 0.33,
        "vol_ratio": 1.56,
        "pe": 10.95,
        "pe_ttm": 3.42,
        "pb": 0.44,
        "total_cap": 6855000000.0,
        "float_cap": 7343000000.000001,
        "main_net": null,
        "concepts": [
          "建筑装饰",
          "基础建设",
          "基建市政工程",
          "山东板块",
          "长期破净",
          "破净股"
        ],
        "score": 44.07,
        "holder_num": 43698.0,
        "holder_change_ratio": -2.127754882638,
        "holder_avg_shares": 35526.6021557051,
        "holder_date": "2026-03-31"
      },
      {
        "code": "603697",
        "name": "有友食品",
        "price": 9.62,
        "pct": -6.87,
        "amount": 55390000.0,
        "turnover": 1.31,
        "vol_ratio": 1.64,
        "pe": 15.64,
        "pe_ttm": 20.47,
        "pb": 2.34,
        "total_cap": 4114000000.0,
        "float_cap": 4114000000.0,
        "main_net": null,
        "concepts": [
          "食品饮料",
          "休闲食品",
          "零食",
          "重庆板块",
          "昨日高振幅",
          "沪股通"
        ],
        "score": 43.67,
        "holder_num": 23845.0,
        "holder_change_ratio": -4.600920184037,
        "holder_avg_shares": 17936.3429649822,
        "holder_date": "2026-03-31"
      },
      {
        "code": "002817",
        "name": "黄山胶囊",
        "price": 5.78,
        "pct": -3.18,
        "amount": 32660000.0,
        "turnover": 1.92,
        "vol_ratio": 1.62,
        "pe": 24.89,
        "pe_ttm": 27.22,
        "pb": 1.8,
        "total_cap": 1676000000.0000002,
        "float_cap": 1729000000.0,
        "main_net": null,
        "concepts": [
          "医药生物",
          "化学制药",
          "原料药",
          "安徽板块",
          "昨日高振幅",
          "专精特新"
        ],
        "score": 41.87,
        "holder_num": 18494.0,
        "holder_change_ratio": -2.785954583684,
        "holder_avg_shares": 16172.7138531416,
        "holder_date": "2026-03-31"
      },
      {
        "code": "002649",
        "name": "博彦科技",
        "price": 8.18,
        "pct": 3.15,
        "amount": 96810000.0,
        "turnover": 2.2,
        "vol_ratio": 2.19,
        "pe": 104.05,
        "pe_ttm": 109.78,
        "pb": 1.17,
        "total_cap": 4387000000.0,
        "float_cap": 4838000000.0,
        "main_net": null,
        "concepts": [
          "计算机",
          "IT服务Ⅱ",
          "IT服务Ⅲ",
          "北京板块",
          "深股通",
          "融资融券"
        ],
        "score": 41.41,
        "holder_num": 55152.0,
        "holder_change_ratio": -1.864768683274,
        "holder_avg_shares": 10613.296562228,
        "holder_date": "2026-04-30"
      },
      {
        "code": "002383",
        "name": "合众思壮",
        "price": 6.77,
        "pct": 2.27,
        "amount": 79940000.0,
        "turnover": 1.58,
        "vol_ratio": 2.12,
        "pe": 2960.59,
        "pe_ttm": -31.23,
        "pb": 3.34,
        "total_cap": 5012000000.0,
        "float_cap": 5012000000.0,
        "main_net": null,
        "concepts": [
          "国防军工",
          "军工电子Ⅱ",
          "军工电子Ⅲ",
          "北京板块",
          "破发股",
          "微利股"
        ],
        "score": 41.31,
        "holder_num": 85892.0,
        "holder_change_ratio": -9.185874392049,
        "holder_avg_shares": 8619.66545196293,
        "holder_date": "2026-03-31"
      },
      {
        "code": "300022",
        "name": "吉峰科技",
        "price": 7.69,
        "pct": 2.67,
        "amount": 121590000.0,
        "turnover": 3.17,
        "vol_ratio": 2.74,
        "pe": 225.03,
        "pe_ttm": -121.21,
        "pb": 7.44,
        "total_cap": 3801000000.0,
        "float_cap": 3801000000.0,
        "main_net": null,
        "concepts": [
          "商贸零售",
          "专业连锁Ⅱ",
          "专业连锁Ⅲ",
          "四川板块",
          "内贸流通",
          "创业板综"
        ],
        "score": 41.01,
        "holder_num": 21404.0,
        "holder_change_ratio": -0.815569972196,
        "holder_avg_shares": 23091.0287796674,
        "holder_date": "2026-05-20"
      },
      {
        "code": "002567",
        "name": "唐人神",
        "price": 3.36,
        "pct": 0.3,
        "amount": 57750000.0,
        "turnover": 1.21,
        "vol_ratio": 1.64,
        "pe": -1.92,
        "pe_ttm": -2.77,
        "pb": 1.16,
        "total_cap": 4810000000.0,
        "float_cap": 4815000000.0,
        "main_net": null,
        "concepts": [
          "农林牧渔",
          "饲料",
          "畜禽饲料",
          "湖南板块",
          "破增发价股",
          "破发股"
        ],
        "score": 40.82,
        "holder_num": 74419.0,
        "holder_change_ratio": -0.442809364548,
        "holder_avg_shares": 19256.5257931442,
        "holder_date": "2026-03-31"
      },
      {
        "code": "002825",
        "name": "纳尔股份",
        "price": 8.2,
        "pct": 2.12,
        "amount": 25390000.0,
        "turnover": 1.21,
        "vol_ratio": 1.58,
        "pe": 40.45,
        "pe_ttm": 31.34,
        "pb": 1.73,
        "total_cap": 2104000000.0,
        "float_cap": 2804000000.0,
        "main_net": null,
        "concepts": [
          "基础化工",
          "塑料",
          "其他塑料制品",
          "上海板块",
          "专精特新",
          "举牌"
        ],
        "score": 40.2,
        "holder_num": 22178.0,
        "holder_change_ratio": -5.242469557787,
        "holder_avg_shares": 15399.7261700785,
        "holder_date": "2026-03-31"
      },
      {
        "code": "300175",
        "name": "朗源股份",
        "price": 4.65,
        "pct": 0.87,
        "amount": 47860000.0,
        "turnover": 2.15,
        "vol_ratio": 2.06,
        "pe": -97.47,
        "pe_ttm": -131.03,
        "pb": 4.39,
        "total_cap": 2189000000.0,
        "float_cap": 2189000000.0,
        "main_net": null,
        "concepts": [
          "农林牧渔",
          "农产品加工",
          "果蔬加工",
          "山东板块",
          "微盘股",
          "农业种植"
        ],
        "score": 39.47,
        "holder_num": 13884.0,
        "holder_change_ratio": -7.667752876239,
        "holder_avg_shares": 33909.5361567272,
        "holder_date": "2026-03-31"
      },
      {
        "code": "000897",
        "name": "津滨发展",
        "price": 1.67,
        "pct": 0.0,
        "amount": 38550000.0,
        "turnover": 1.41,
        "vol_ratio": 1.9,
        "pe": -421.13,
        "pe_ttm": -46.31,
        "pb": 0.9,
        "total_cap": 2701000000.0,
        "float_cap": 2701000000.0,
        "main_net": null,
        "concepts": [
          "房地产",
          "房地产开发",
          "住宅开发",
          "天津板块",
          "破净股",
          "低价股"
        ],
        "score": 38.43,
        "holder_num": 79406.0,
        "holder_change_ratio": -0.093105183694,
        "holder_avg_shares": 20367.1288567615,
        "holder_date": "2026-03-31"
      },
      {
        "code": "603577",
        "name": "汇金通",
        "price": 9.23,
        "pct": 7.83,
        "amount": 57890000.0,
        "turnover": 1.89,
        "vol_ratio": 3.36,
        "pe": 57.53,
        "pe_ttm": 30.78,
        "pb": 1.6,
        "total_cap": 3130000000.0,
        "float_cap": 3130000000.0,
        "main_net": null,
        "concepts": [
          "电力设备",
          "电网设备",
          "线缆部件及其他",
          "山东板块",
          "电网概念",
          "特高压"
        ],
        "score": 38.23,
        "holder_num": 15500.0,
        "holder_change_ratio": -2.924782363625,
        "holder_avg_shares": 21879.9419354839,
        "holder_date": "2026-06-18"
      },
      {
        "code": "600833",
        "name": "第一医药",
        "price": 8.96,
        "pct": -3.55,
        "amount": 23910000.0,
        "turnover": 1.18,
        "vol_ratio": 1.56,
        "pe": 21.48,
        "pe_ttm": 26.21,
        "pb": 1.72,
        "total_cap": 1998999999.9999998,
        "float_cap": 1998999999.9999998,
        "main_net": null,
        "concepts": [
          "医药生物",
          "医药商业",
          "线下药店",
          "上海板块",
          "2025年报预减",
          "内贸流通"
        ],
        "score": 37.82,
        "holder_num": 22478.0,
        "holder_change_ratio": -2.468867965462,
        "holder_avg_shares": 9924.65286057478,
        "holder_date": "2026-03-31"
      },
      {
        "code": "300256",
        "name": "星星科技",
        "price": 2.6,
        "pct": 2.36,
        "amount": 62310000.0,
        "turnover": 1.07,
        "vol_ratio": 1.88,
        "pe": -79.66,
        "pe_ttm": -137.63,
        "pb": 6.5,
        "total_cap": 5833000000.0,
        "float_cap": 5898000000.0,
        "main_net": null,
        "concepts": [
          "电子",
          "消费电子",
          "消费电子零部件及组装",
          "江西板块",
          "破发股",
          "低价股"
        ],
        "score": 37.13,
        "holder_num": 79805.0,
        "holder_change_ratio": -9.450382372297,
        "holder_avg_shares": 28424.201315707,
        "holder_date": "2026-03-31"
      },
      {
        "code": "002117",
        "name": "东港股份",
        "price": 7.94,
        "pct": 2.58,
        "amount": 48860000.0,
        "turnover": 1.19,
        "vol_ratio": 1.55,
        "pe": 20.95,
        "pe_ttm": 27.57,
        "pb": 3.14,
        "total_cap": 4157000000.0,
        "float_cap": 4158000000.0,
        "main_net": null,
        "concepts": [
          "轻工制造",
          "包装印刷",
          "印刷",
          "山东板块",
          "富时罗素",
          "深股通"
        ],
        "score": 36.34,
        "holder_num": 32377.0,
        "holder_change_ratio": -1.490857090699,
        "holder_avg_shares": 16175.7097631034,
        "holder_date": "2026-06-18"
      },
      {
        "code": "603811",
        "name": "诚意药业",
        "price": 7.44,
        "pct": -4.0,
        "amount": 34130000.0,
        "turnover": 0.99,
        "vol_ratio": 1.8,
        "pe": 19.24,
        "pe_ttm": 17.61,
        "pb": 2.52,
        "total_cap": 3409000000.0000005,
        "float_cap": 3409000000.0000005,
        "main_net": null,
        "concepts": [
          "医药生物",
          "化学制药",
          "化学制剂",
          "浙江板块",
          "昨日高振幅",
          "参股新三板"
        ],
        "score": 36.22,
        "holder_num": 23965.0,
        "holder_change_ratio": -2.521862924547,
        "holder_avg_shares": 13657.5973294388,
        "holder_date": "2026-03-31"
      },
      {
        "code": "603385",
        "name": "惠达卫浴",
        "price": 4.9,
        "pct": -1.21,
        "amount": 20340000.0,
        "turnover": 1.08,
        "vol_ratio": 1.69,
        "pe": -15.3,
        "pe_ttm": -8.07,
        "pb": 0.53,
        "total_cap": 1864999999.9999998,
        "float_cap": 1864999999.9999998,
        "main_net": null,
        "concepts": [
          "轻工制造",
          "家居用品",
          "卫浴制品",
          "河北板块",
          "破增发价股",
          "破发股"
        ],
        "score": 35.88,
        "holder_num": 14418.0,
        "holder_change_ratio": -1.016064808458,
        "holder_avg_shares": 26402.0646414204,
        "holder_date": "2026-03-31"
      },
      {
        "code": "603030",
        "name": "全筑股份",
        "price": 1.96,
        "pct": -1.01,
        "amount": 58070000.0,
        "turnover": 2.22,
        "vol_ratio": 1.73,
        "pe": 287.13,
        "pe_ttm": -9.61,
        "pb": 3.69,
        "total_cap": 2581000000.0,
        "float_cap": 2581000000.0,
        "main_net": null,
        "concepts": [
          "建筑装饰",
          "装修装饰Ⅱ",
          "装修装饰Ⅲ",
          "上海板块",
          "破发股",
          "低价股"
        ],
        "score": 34.94,
        "holder_num": 35384.0,
        "holder_change_ratio": -5.627567077399,
        "holder_avg_shares": 37218.3337101515,
        "holder_date": "2026-03-31"
      },
      {
        "code": "002855",
        "name": "捷荣技术",
        "price": 9.56,
        "pct": 1.7,
        "amount": 36780000.0,
        "turnover": 1.54,
        "vol_ratio": 1.8,
        "pe": -31.95,
        "pe_ttm": -5.59,
        "pb": 11.37,
        "total_cap": 2354000000.0,
        "float_cap": 2356000000.0,
        "main_net": null,
        "concepts": [
          "电子",
          "消费电子",
          "消费电子零部件及组装",
          "广东板块",
          "超跌股",
          "昨日高振幅"
        ],
        "score": 34.8,
        "holder_num": 32107.0,
        "holder_change_ratio": -10.468196648169,
        "holder_avg_shares": 7674.95194194412,
        "holder_date": "2026-03-31"
      },
      {
        "code": "600661",
        "name": "昂立教育",
        "price": 6.93,
        "pct": -1.42,
        "amount": 42060000.0,
        "turnover": 2.07,
        "vol_ratio": 1.79,
        "pe": 20.18,
        "pe_ttm": 20.29,
        "pb": 7.79,
        "total_cap": 1986000000.0,
        "float_cap": 1986000000.0,
        "main_net": null,
        "concepts": [
          "社会服务",
          "教育",
          "培训教育",
          "上海板块",
          "2025年报扭亏",
          "破增发价股"
        ],
        "score": 32.24,
        "holder_num": 21273.0,
        "holder_change_ratio": -6.286343612335,
        "holder_avg_shares": 13470.0714520754,
        "holder_date": "2026-03-31"
      },
      {
        "code": "002793",
        "name": "罗欣药业",
        "price": 3.81,
        "pct": -4.99,
        "amount": 59960000.0,
        "turnover": 1.42,
        "vol_ratio": 1.52,
        "pe": 42.9,
        "pe_ttm": -15.34,
        "pb": 3.77,
        "total_cap": 4136999999.9999995,
        "float_cap": 4144000000.0,
        "main_net": null,
        "concepts": [
          "医药生物",
          "化学制药",
          "化学制剂",
          "山东板块",
          "昨日高振幅",
          "2025三季报扭亏"
        ],
        "score": 31.15,
        "holder_num": 35063.0,
        "holder_change_ratio": -1.676901937691,
        "holder_avg_shares": 31018.1241194422,
        "holder_date": "2026-06-18"
      },
      {
        "code": "300314",
        "name": "戴维医疗",
        "price": 9.35,
        "pct": -4.1,
        "amount": 29540000.0,
        "turnover": 2.15,
        "vol_ratio": 1.63,
        "pe": 68.1,
        "pe_ttm": 36.21,
        "pb": 2.21,
        "total_cap": 1344000000.0,
        "float_cap": 2693000000.0,
        "main_net": null,
        "concepts": [
          "医药生物",
          "医疗器械",
          "医疗设备",
          "浙江板块",
          "2025年报预增",
          "昨日高振幅"
        ],
        "score": 30.22,
        "holder_num": 16600.0,
        "holder_change_ratio": -1.190476190476,
        "holder_avg_shares": 17349.3975903614,
        "holder_date": "2026-06-18"
      },
      {
        "code": "002178",
        "name": "延华智能",
        "price": 4.35,
        "pct": -1.58,
        "amount": 49660000.0,
        "turnover": 1.6,
        "vol_ratio": 1.84,
        "pe": -135.91,
        "pe_ttm": 372.47,
        "pb": 7.17,
        "total_cap": 3096000000.0,
        "float_cap": 3098000000.0,
        "main_net": null,
        "concepts": [
          "计算机",
          "软件开发",
          "垂直应用软件",
          "上海板块",
          "2025年报扭亏",
          "创新医疗服务"
        ],
        "score": 29.96,
        "holder_num": 96479.0,
        "holder_change_ratio": -4.985178400843,
        "holder_avg_shares": 7381.43016615015,
        "holder_date": "2026-03-31"
      },
      {
        "code": "300426",
        "name": "华智数媒",
        "price": 5.06,
        "pct": -1.17,
        "amount": 53070000.0,
        "turnover": 2.55,
        "vol_ratio": 1.58,
        "pe": -33.98,
        "pe_ttm": -5.74,
        "pb": 24.52,
        "total_cap": 2023999999.9999998,
        "float_cap": 2279000000.0,
        "main_net": null,
        "concepts": [
          "传媒",
          "影视院线",
          "影视动漫制作",
          "浙江板块",
          "破增发价股",
          "创业板综"
        ],
        "score": 29.83,
        "holder_num": 15681.0,
        "holder_change_ratio": -2.030488566787,
        "holder_avg_shares": 28721.5617626427,
        "holder_date": "2026-06-18"
      },
      {
        "code": "600854",
        "name": "春兰股份",
        "price": 4.06,
        "pct": -1.93,
        "amount": 49680000.0,
        "turnover": 2.32,
        "vol_ratio": 2.07,
        "pe": 359.28,
        "pe_ttm": 16.72,
        "pb": 0.87,
        "total_cap": 2109000000.0,
        "float_cap": 2109000000.0,
        "main_net": null,
        "concepts": [
          "房地产",
          "房地产开发",
          "住宅开发",
          "江苏板块",
          "微利股",
          "昨日高振幅"
        ],
        "score": 25.78,
        "holder_num": 23850.0,
        "holder_change_ratio": -0.703609642366,
        "holder_avg_shares": 21780.2322012579,
        "holder_date": "2026-03-31"
      },
      {
        "code": "000972",
        "name": "中基健康",
        "price": 3.13,
        "pct": -4.86,
        "amount": 35870000.0,
        "turnover": 1.47,
        "vol_ratio": 2.6,
        "pe": -30.75,
        "pe_ttm": -41.19,
        "pb": 371.82,
        "total_cap": 2414000000.0,
        "float_cap": 2414000000.0,
        "main_net": null,
        "concepts": [
          "农林牧渔",
          "农产品加工",
          "果蔬加工",
          "新疆板块",
          "央国企改革",
          "医疗器械概念"
        ],
        "score": 24.93,
        "holder_num": 22026.0,
        "holder_change_ratio": -5.162540365985,
        "holder_avg_shares": 35016.9608190321,
        "holder_date": "2026-06-18"
      },
      {
        "code": "002659",
        "name": "凯文教育",
        "price": 3.72,
        "pct": -0.8,
        "amount": 40550000.0,
        "turnover": 1.79,
        "vol_ratio": 1.61,
        "pe": 2884.08,
        "pe_ttm": -128.54,
        "pb": 1.04,
        "total_cap": 2226000000.0,
        "float_cap": 2226000000.0,
        "main_net": null,
        "concepts": [
          "社会服务",
          "教育",
          "学历教育",
          "北京板块",
          "破增发价股",
          "破发股"
        ],
        "score": 23.29,
        "holder_num": 22139.0,
        "holder_change_ratio": -0.873108265425,
        "holder_avg_shares": 27023.8214914856,
        "holder_date": "2026-06-10"
      },
      {
        "code": "601956",
        "name": "XD东贝集",
        "price": 4.58,
        "pct": -0.65,
        "amount": 29140000.0,
        "turnover": 1.01,
        "vol_ratio": 1.69,
        "pe": -42.39,
        "pe_ttm": 203.99,
        "pb": 1.18,
        "total_cap": 2847000000.0,
        "float_cap": 2847000000.0,
        "main_net": null,
        "concepts": [
          "家用电器",
          "家电零部件Ⅱ",
          "家电零部件Ⅲ",
          "湖北板块",
          "破增发价股",
          "破发股"
        ],
        "score": 22.13,
        "holder_num": 30691.0,
        "holder_change_ratio": -3.16463683978,
        "holder_avg_shares": 20254.0350591379,
        "holder_date": "2026-06-20"
      }
    ],
    "5": [
      {
        "code": "002437",
        "name": "誉衡药业",
        "price": 2.66,
        "pct": -0.37,
        "amount": 305980000.0,
        "turnover": 5.33,
        "vol_ratio": 2.47,
        "pe": 15.62,
        "pe_ttm": 14.41,
        "pb": 2.48,
        "total_cap": 5586000000.0,
        "float_cap": 5931000000.0,
        "main_net": null,
        "concepts": [],
        "score": 99.76,
        "holder_num": 91300.0,
        "holder_change_ratio": -2.038626609442,
        "holder_avg_shares": 24423.5282146769,
        "holder_date": "2026-06-20"
      },
      {
        "code": "000566",
        "name": "海南海药",
        "price": 4.6,
        "pct": 1.32,
        "amount": 610150000.0,
        "turnover": 9.98,
        "vol_ratio": 2.89,
        "pe": -19.52,
        "pe_ttm": -13.62,
        "pb": 1341.87,
        "total_cap": 5965000000.0,
        "float_cap": 5968000000.0,
        "main_net": null,
        "concepts": [],
        "score": 95.34,
        "holder_num": 112860.0,
        "holder_change_ratio": -3.914590747331,
        "holder_avg_shares": 11495.3493354599,
        "holder_date": "2026-03-31"
      },
      {
        "code": "002607",
        "name": "中公教育",
        "price": 1.77,
        "pct": -2.21,
        "amount": 477610000.0,
        "turnover": 4.68,
        "vol_ratio": 3.06,
        "pe": 57.67,
        "pe_ttm": 194.16,
        "pb": 13.57,
        "total_cap": 9812000000.0,
        "float_cap": 10916000000.0,
        "main_net": null,
        "concepts": [],
        "score": 85.28,
        "holder_num": 256307.0,
        "holder_change_ratio": -5.161753442094,
        "holder_avg_shares": 24062.5476050205,
        "holder_date": "2026-03-31"
      },
      {
        "code": "000727",
        "name": "冠捷科技",
        "price": 2.7,
        "pct": 6.72,
        "amount": 557070000.0,
        "turnover": 4.62,
        "vol_ratio": 2.28,
        "pe": -10.81,
        "pe_ttm": -13.63,
        "pb": 6.78,
        "total_cap": 12230000000.0,
        "float_cap": 12230000000.0,
        "main_net": null,
        "concepts": [],
        "score": 84.11,
        "holder_num": 134000.0,
        "holder_change_ratio": -6.293706293706,
        "holder_avg_shares": 33802.7386567164,
        "holder_date": "2026-06-18"
      },
      {
        "code": "600376",
        "name": "首开股份",
        "price": 3.37,
        "pct": 4.01,
        "amount": 242880000.0,
        "turnover": 2.85,
        "vol_ratio": 2.42,
        "pe": -2.88,
        "pe_ttm": -1.38,
        "pb": 3.69,
        "total_cap": 8693000000.0,
        "float_cap": 8693000000.0,
        "main_net": null,
        "concepts": [],
        "score": 80.17,
        "holder_num": 145614.0,
        "holder_change_ratio": -23.515631565678,
        "holder_avg_shares": 17715.0908703833,
        "holder_date": "2026-03-31"
      },
      {
        "code": "688538",
        "name": "和辉光电-U",
        "price": 2.59,
        "pct": 5.71,
        "amount": 490110000.0,
        "turnover": 3.31,
        "vol_ratio": 2.45,
        "pe": -19.03,
        "pe_ttm": -18.49,
        "pb": 4.71,
        "total_cap": 14897999999.999998,
        "float_cap": 35766000000.0,
        "main_net": null,
        "concepts": [],
        "score": 79.06,
        "holder_num": 107703.0,
        "holder_change_ratio": -2.435864917748,
        "holder_avg_shares": 128217.762040055,
        "holder_date": "2026-03-31"
      },
      {
        "code": "002146",
        "name": "荣盛发展",
        "price": 1.07,
        "pct": 2.88,
        "amount": 146270000.0,
        "turnover": 3.43,
        "vol_ratio": 2.44,
        "pe": -1.77,
        "pe_ttm": -0.51,
        "pb": 0.92,
        "total_cap": 4185000000.0,
        "float_cap": 4653000000.0,
        "main_net": null,
        "concepts": [],
        "score": 77.29,
        "holder_num": 135944.0,
        "holder_change_ratio": -12.060444536445,
        "holder_avg_shares": 31984.9633010651,
        "holder_date": "2026-03-31"
      },
      {
        "code": "000420",
        "name": "吉林化纤",
        "price": 4.06,
        "pct": -3.33,
        "amount": 329860000.0,
        "turnover": 3.32,
        "vol_ratio": 1.72,
        "pe": 91.59,
        "pe_ttm": 239.34,
        "pb": 2.25,
        "total_cap": 9980000000.0,
        "float_cap": 9983000000.0,
        "main_net": null,
        "concepts": [],
        "score": 76.64,
        "holder_num": 141307.0,
        "holder_change_ratio": -0.788457487889,
        "holder_avg_shares": 17400.8955182687,
        "holder_date": "2026-03-31"
      },
      {
        "code": "000863",
        "name": "三湘印象",
        "price": 4.17,
        "pct": 2.71,
        "amount": 81920000.0,
        "turnover": 1.68,
        "vol_ratio": 1.59,
        "pe": -242.43,
        "pe_ttm": -31.88,
        "pb": 1.13,
        "total_cap": 4851000000.0,
        "float_cap": 4924000000.0,
        "main_net": null,
        "concepts": [],
        "score": 59.38,
        "holder_num": 25253.0,
        "holder_change_ratio": -32.926958831341,
        "holder_avg_shares": 46754.8235853166,
        "holder_date": "2026-03-31"
      },
      {
        "code": "600076",
        "name": "康欣新材",
        "price": 3.31,
        "pct": 9.97,
        "amount": 133010000.0,
        "turnover": 3.09,
        "vol_ratio": 1.93,
        "pe": -21.44,
        "pe_ttm": -11.38,
        "pb": 1.25,
        "total_cap": 4450000000.0,
        "float_cap": 4450000000.0,
        "main_net": null,
        "concepts": [],
        "score": 57.61,
        "holder_num": 48654.0,
        "holder_change_ratio": -3.447044115021,
        "holder_avg_shares": 27634.7960496568,
        "holder_date": "2026-06-10"
      },
      {
        "code": "002863",
        "name": "今飞凯达",
        "price": 4.22,
        "pct": -1.17,
        "amount": 35720000.0,
        "turnover": 1.41,
        "vol_ratio": 1.52,
        "pe": 21.51,
        "pe_ttm": 39.54,
        "pb": 0.9,
        "total_cap": 2530000000.0,
        "float_cap": 2530000000.0,
        "main_net": null,
        "concepts": [],
        "score": 57.08,
        "holder_num": 28906.0,
        "holder_change_ratio": -11.09402392889,
        "holder_avg_shares": 20739.0698816855,
        "holder_date": "2026-03-31"
      },
      {
        "code": "000090",
        "name": "天健集团",
        "price": 3.0,
        "pct": -3.54,
        "amount": 46210000.0,
        "turnover": 0.82,
        "vol_ratio": 1.51,
        "pe": -60.11,
        "pe_ttm": 35.08,
        "pb": 0.5,
        "total_cap": 5605000000.0,
        "float_cap": 5606000000.0,
        "main_net": null,
        "concepts": [],
        "score": 55.12,
        "holder_num": 39728.0,
        "holder_change_ratio": -10.781737743942,
        "holder_avg_shares": 47033.4634011277,
        "holder_date": "2026-03-31"
      },
      {
        "code": "600966",
        "name": "博汇纸业",
        "price": 4.75,
        "pct": -5.0,
        "amount": 53460000.0,
        "turnover": 0.83,
        "vol_ratio": 1.83,
        "pe": 28.67,
        "pe_ttm": 40.32,
        "pb": 0.85,
        "total_cap": 6350000000.0,
        "float_cap": 6350000000.0,
        "main_net": null,
        "concepts": [],
        "score": 54.87,
        "holder_num": 41508.0,
        "holder_change_ratio": -9.674892283588,
        "holder_avg_shares": 32206.9068131445,
        "holder_date": "2026-03-31"
      },
      {
        "code": "000536",
        "name": "华映科技",
        "price": 3.25,
        "pct": 5.18,
        "amount": 220800000.0,
        "turnover": 2.44,
        "vol_ratio": 2.19,
        "pe": -10.12,
        "pe_ttm": -8.81,
        "pb": 10.7,
        "total_cap": 8980000000.0,
        "float_cap": 8990000000.0,
        "main_net": null,
        "concepts": [],
        "score": 53.3,
        "holder_num": 216480.0,
        "holder_change_ratio": -0.162337662338,
        "holder_avg_shares": 12777.3133915373,
        "holder_date": "2026-06-18"
      },
      {
        "code": "300071",
        "name": "福石控股",
        "price": 3.51,
        "pct": 3.24,
        "amount": 108090000.0,
        "turnover": 3.25,
        "vol_ratio": 1.92,
        "pe": -1278.6,
        "pe_ttm": -29.79,
        "pb": 21.02,
        "total_cap": 3318000000.0,
        "float_cap": 3383000000.0,
        "main_net": null,
        "concepts": [],
        "score": 52.38,
        "holder_num": 72629.0,
        "holder_change_ratio": -11.925348338043,
        "holder_avg_shares": 13271.3425215823,
        "holder_date": "2026-03-31"
      },
      {
        "code": "002427",
        "name": "尤夫股份",
        "price": 4.97,
        "pct": -5.69,
        "amount": 168460000.0,
        "turnover": 3.43,
        "vol_ratio": 1.64,
        "pe": -61.05,
        "pe_ttm": 385.44,
        "pb": 5.17,
        "total_cap": 4893000000.0,
        "float_cap": 4898000000.0,
        "main_net": null,
        "concepts": [],
        "score": 52.2,
        "holder_num": 56181.0,
        "holder_change_ratio": -3.699069233274,
        "holder_avg_shares": 17540.3210516011,
        "holder_date": "2026-03-31"
      },
      {
        "code": "002548",
        "name": "金新农",
        "price": 3.68,
        "pct": 1.66,
        "amount": 79360000.0,
        "turnover": 2.66,
        "vol_ratio": 1.52,
        "pe": -4.13,
        "pe_ttm": -6.75,
        "pb": 2.91,
        "total_cap": 2960000000.0,
        "float_cap": 3048000000.0,
        "main_net": null,
        "concepts": [],
        "score": 50.33,
        "holder_num": 48916.0,
        "holder_change_ratio": -6.38265296358,
        "holder_avg_shares": 16930.5269850356,
        "holder_date": "2026-05-10"
      },
      {
        "code": "002688",
        "name": "金河生物",
        "price": 4.62,
        "pct": -4.15,
        "amount": 37690000.0,
        "turnover": 1.08,
        "vol_ratio": 1.76,
        "pe": 14.27,
        "pe_ttm": 91.78,
        "pb": 1.61,
        "total_cap": 3453000000.0,
        "float_cap": 3554999999.9999995,
        "main_net": null,
        "concepts": [],
        "score": 49.09,
        "holder_num": 47987.0,
        "holder_change_ratio": -7.489589759408,
        "holder_avg_shares": 16035.6846229187,
        "holder_date": "2026-03-31"
      },
      {
        "code": "601005",
        "name": "重庆钢铁",
        "price": 1.16,
        "pct": 0.87,
        "amount": 88540000.0,
        "turnover": 0.91,
        "vol_ratio": 1.81,
        "pe": -13.99,
        "pe_ttm": -3.98,
        "pb": 0.76,
        "total_cap": 9644000000.0,
        "float_cap": 11147000000.0,
        "main_net": null,
        "concepts": [],
        "score": 48.77,
        "holder_num": 167136.0,
        "holder_change_ratio": -0.77121738356,
        "holder_avg_shares": 50141.6515113441,
        "holder_date": "2024-02-08"
      },
      {
        "code": "000036",
        "name": "华联控股",
        "price": 4.34,
        "pct": -2.91,
        "amount": 88400000.0,
        "turnover": 1.43,
        "vol_ratio": 1.7,
        "pe": 58.5,
        "pe_ttm": 67.36,
        "pb": 1.18,
        "total_cap": 6089000000.0,
        "float_cap": 6093000000.0,
        "main_net": null,
        "concepts": [],
        "score": 48.0,
        "holder_num": 46139.0,
        "holder_change_ratio": -3.325231529984,
        "holder_avg_shares": 30425.8593597607,
        "holder_date": "2026-05-20"
      },
      {
        "code": "601599",
        "name": "浙文影业",
        "price": 2.76,
        "pct": -2.13,
        "amount": 35040000.0,
        "turnover": 1.08,
        "vol_ratio": 1.62,
        "pe": 44.77,
        "pe_ttm": 28.75,
        "pb": 2.09,
        "total_cap": 3203000000.0,
        "float_cap": 3203000000.0,
        "main_net": null,
        "concepts": [],
        "score": 46.3,
        "holder_num": 47198.0,
        "holder_change_ratio": -18.451198230731,
        "holder_avg_shares": 24588.8057332938,
        "holder_date": "2026-03-31"
      },
      {
        "code": "000498",
        "name": "山东路桥",
        "price": 4.73,
        "pct": -1.87,
        "amount": 22870000.0,
        "turnover": 0.33,
        "vol_ratio": 1.56,
        "pe": 10.95,
        "pe_ttm": 3.42,
        "pb": 0.44,
        "total_cap": 6855000000.0,
        "float_cap": 7343000000.000001,
        "main_net": null,
        "concepts": [],
        "score": 44.07,
        "holder_num": 43698.0,
        "holder_change_ratio": -2.127754882638,
        "holder_avg_shares": 35526.6021557051,
        "holder_date": "2026-03-31"
      },
      {
        "code": "002567",
        "name": "唐人神",
        "price": 3.36,
        "pct": 0.3,
        "amount": 57750000.0,
        "turnover": 1.21,
        "vol_ratio": 1.64,
        "pe": -1.92,
        "pe_ttm": -2.77,
        "pb": 1.16,
        "total_cap": 4810000000.0,
        "float_cap": 4815000000.0,
        "main_net": null,
        "concepts": [],
        "score": 40.82,
        "holder_num": 74419.0,
        "holder_change_ratio": -0.442809364548,
        "holder_avg_shares": 19256.5257931442,
        "holder_date": "2026-03-31"
      },
      {
        "code": "300175",
        "name": "朗源股份",
        "price": 4.65,
        "pct": 0.87,
        "amount": 47860000.0,
        "turnover": 2.15,
        "vol_ratio": 2.06,
        "pe": -97.47,
        "pe_ttm": -131.03,
        "pb": 4.39,
        "total_cap": 2189000000.0,
        "float_cap": 2189000000.0,
        "main_net": null,
        "concepts": [],
        "score": 39.47,
        "holder_num": 13884.0,
        "holder_change_ratio": -7.667752876239,
        "holder_avg_shares": 33909.5361567272,
        "holder_date": "2026-03-31"
      },
      {
        "code": "000897",
        "name": "津滨发展",
        "price": 1.67,
        "pct": 0.0,
        "amount": 38550000.0,
        "turnover": 1.41,
        "vol_ratio": 1.9,
        "pe": -421.13,
        "pe_ttm": -46.31,
        "pb": 0.9,
        "total_cap": 2701000000.0,
        "float_cap": 2701000000.0,
        "main_net": null,
        "concepts": [],
        "score": 38.43,
        "holder_num": 79406.0,
        "holder_change_ratio": -0.093105183694,
        "holder_avg_shares": 20367.1288567615,
        "holder_date": "2026-03-31"
      },
      {
        "code": "300256",
        "name": "星星科技",
        "price": 2.6,
        "pct": 2.36,
        "amount": 62310000.0,
        "turnover": 1.07,
        "vol_ratio": 1.88,
        "pe": -79.66,
        "pe_ttm": -137.63,
        "pb": 6.5,
        "total_cap": 5833000000.0,
        "float_cap": 5898000000.0,
        "main_net": null,
        "concepts": [],
        "score": 37.13,
        "holder_num": 79805.0,
        "holder_change_ratio": -9.450382372297,
        "holder_avg_shares": 28424.201315707,
        "holder_date": "2026-03-31"
      },
      {
        "code": "603385",
        "name": "惠达卫浴",
        "price": 4.9,
        "pct": -1.21,
        "amount": 20340000.0,
        "turnover": 1.08,
        "vol_ratio": 1.69,
        "pe": -15.3,
        "pe_ttm": -8.07,
        "pb": 0.53,
        "total_cap": 1864999999.9999998,
        "float_cap": 1864999999.9999998,
        "main_net": null,
        "concepts": [],
        "score": 35.88,
        "holder_num": 14418.0,
        "holder_change_ratio": -1.016064808458,
        "holder_avg_shares": 26402.0646414204,
        "holder_date": "2026-03-31"
      },
      {
        "code": "603030",
        "name": "全筑股份",
        "price": 1.96,
        "pct": -1.01,
        "amount": 58070000.0,
        "turnover": 2.22,
        "vol_ratio": 1.73,
        "pe": 287.13,
        "pe_ttm": -9.61,
        "pb": 3.69,
        "total_cap": 2581000000.0,
        "float_cap": 2581000000.0,
        "main_net": null,
        "concepts": [],
        "score": 34.94,
        "holder_num": 35384.0,
        "holder_change_ratio": -5.627567077399,
        "holder_avg_shares": 37218.3337101515,
        "holder_date": "2026-03-31"
      },
      {
        "code": "002793",
        "name": "罗欣药业",
        "price": 3.81,
        "pct": -4.99,
        "amount": 59960000.0,
        "turnover": 1.42,
        "vol_ratio": 1.52,
        "pe": 42.9,
        "pe_ttm": -15.34,
        "pb": 3.77,
        "total_cap": 4136999999.9999995,
        "float_cap": 4144000000.0,
        "main_net": null,
        "concepts": [],
        "score": 31.15,
        "holder_num": 35063.0,
        "holder_change_ratio": -1.676901937691,
        "holder_avg_shares": 31018.1241194422,
        "holder_date": "2026-06-18"
      },
      {
        "code": "002178",
        "name": "延华智能",
        "price": 4.35,
        "pct": -1.58,
        "amount": 49660000.0,
        "turnover": 1.6,
        "vol_ratio": 1.84,
        "pe": -135.91,
        "pe_ttm": 372.47,
        "pb": 7.17,
        "total_cap": 3096000000.0,
        "float_cap": 3098000000.0,
        "main_net": null,
        "concepts": [],
        "score": 29.96,
        "holder_num": 96479.0,
        "holder_change_ratio": -4.985178400843,
        "holder_avg_shares": 7381.43016615015,
        "holder_date": "2026-03-31"
      },
      {
        "code": "600854",
        "name": "春兰股份",
        "price": 4.06,
        "pct": -1.93,
        "amount": 49680000.0,
        "turnover": 2.32,
        "vol_ratio": 2.07,
        "pe": 359.28,
        "pe_ttm": 16.72,
        "pb": 0.87,
        "total_cap": 2109000000.0,
        "float_cap": 2109000000.0,
        "main_net": null,
        "concepts": [],
        "score": 25.78,
        "holder_num": 23850.0,
        "holder_change_ratio": -0.703609642366,
        "holder_avg_shares": 21780.2322012579,
        "holder_date": "2026-03-31"
      },
      {
        "code": "000972",
        "name": "中基健康",
        "price": 3.13,
        "pct": -4.86,
        "amount": 35870000.0,
        "turnover": 1.47,
        "vol_ratio": 2.6,
        "pe": -30.75,
        "pe_ttm": -41.19,
        "pb": 371.82,
        "total_cap": 2414000000.0,
        "float_cap": 2414000000.0,
        "main_net": null,
        "concepts": [],
        "score": 24.93,
        "holder_num": 22026.0,
        "holder_change_ratio": -5.162540365985,
        "holder_avg_shares": 35016.9608190321,
        "holder_date": "2026-06-18"
      },
      {
        "code": "002659",
        "name": "凯文教育",
        "price": 3.72,
        "pct": -0.8,
        "amount": 40550000.0,
        "turnover": 1.79,
        "vol_ratio": 1.61,
        "pe": 2884.08,
        "pe_ttm": -128.54,
        "pb": 1.04,
        "total_cap": 2226000000.0,
        "float_cap": 2226000000.0,
        "main_net": null,
        "concepts": [],
        "score": 23.29,
        "holder_num": 22139.0,
        "holder_change_ratio": -0.873108265425,
        "holder_avg_shares": 27023.8214914856,
        "holder_date": "2026-06-10"
      },
      {
        "code": "601956",
        "name": "XD东贝集",
        "price": 4.58,
        "pct": -0.65,
        "amount": 29140000.0,
        "turnover": 1.01,
        "vol_ratio": 1.69,
        "pe": -42.39,
        "pe_ttm": 203.99,
        "pb": 1.18,
        "total_cap": 2847000000.0,
        "float_cap": 2847000000.0,
        "main_net": null,
        "concepts": [],
        "score": 22.13,
        "holder_num": 30691.0,
        "holder_change_ratio": -3.16463683978,
        "holder_avg_shares": 20254.0350591379,
        "holder_date": "2026-06-20"
      }
    ],
    "2": [
      {
        "code": "002607",
        "name": "中公教育",
        "price": 1.77,
        "pct": -2.21,
        "amount": 477610000.0,
        "turnover": 4.68,
        "vol_ratio": 3.06,
        "pe": 57.67,
        "pe_ttm": 194.16,
        "pb": 13.57,
        "total_cap": 9812000000.0,
        "float_cap": 10916000000.0,
        "main_net": null,
        "concepts": [],
        "score": 85.28,
        "holder_num": 256307.0,
        "holder_change_ratio": -5.161753442094,
        "holder_avg_shares": 24062.5476050205,
        "holder_date": "2026-03-31"
      },
      {
        "code": "002146",
        "name": "荣盛发展",
        "price": 1.07,
        "pct": 2.88,
        "amount": 146270000.0,
        "turnover": 3.43,
        "vol_ratio": 2.44,
        "pe": -1.77,
        "pe_ttm": -0.51,
        "pb": 0.92,
        "total_cap": 4185000000.0,
        "float_cap": 4653000000.0,
        "main_net": null,
        "concepts": [],
        "score": 77.29,
        "holder_num": 135944.0,
        "holder_change_ratio": -12.060444536445,
        "holder_avg_shares": 31984.9633010651,
        "holder_date": "2026-03-31"
      },
      {
        "code": "601005",
        "name": "重庆钢铁",
        "price": 1.16,
        "pct": 0.87,
        "amount": 88540000.0,
        "turnover": 0.91,
        "vol_ratio": 1.81,
        "pe": -13.99,
        "pe_ttm": -3.98,
        "pb": 0.76,
        "total_cap": 9644000000.0,
        "float_cap": 11147000000.0,
        "main_net": null,
        "concepts": [],
        "score": 48.77,
        "holder_num": 167136.0,
        "holder_change_ratio": -0.77121738356,
        "holder_avg_shares": 50141.6515113441,
        "holder_date": "2024-02-08"
      },
      {
        "code": "000897",
        "name": "津滨发展",
        "price": 1.67,
        "pct": 0.0,
        "amount": 38550000.0,
        "turnover": 1.41,
        "vol_ratio": 1.9,
        "pe": -421.13,
        "pe_ttm": -46.31,
        "pb": 0.9,
        "total_cap": 2701000000.0,
        "float_cap": 2701000000.0,
        "main_net": null,
        "concepts": [],
        "score": 38.43,
        "holder_num": 79406.0,
        "holder_change_ratio": -0.093105183694,
        "holder_avg_shares": 20367.1288567615,
        "holder_date": "2026-03-31"
      },
      {
        "code": "603030",
        "name": "全筑股份",
        "price": 1.96,
        "pct": -1.01,
        "amount": 58070000.0,
        "turnover": 2.22,
        "vol_ratio": 1.73,
        "pe": 287.13,
        "pe_ttm": -9.61,
        "pb": 3.69,
        "total_cap": 2581000000.0,
        "float_cap": 2581000000.0,
        "main_net": null,
        "concepts": [],
        "score": 34.94,
        "holder_num": 35384.0,
        "holder_change_ratio": -5.627567077399,
        "holder_avg_shares": 37218.3337101515,
        "holder_date": "2026-03-31"
      }
    ]
  }
}